{"v":"5.12.1","fr":60,"ip":0,"op":120,"w":430,"h":430,"nm":"wired-lineal-653-marriage","ddd":0,"assets":[{"id":"comp_0","nm":"hover-pinch","fr":60,"layers":[{"ddd":0,"ind":1,"ty":4,"nm":"Female 4","td":1,"sr":1,"ks":{"o":{"a":0,"k":100,"ix":11},"r":{"a":0,"k":0,"ix":10},"p":{"a":0,"k":[302.423,401.806,0],"ix":2,"l":2},"a":{"a":0,"k":[337.423,436.806,0],"ix":1,"l":2},"s":{"a":0,"k":[100,100,100],"ix":6,"l":2}},"ao":0,"shapes":[{"ty":"gr","it":[{"ind":0,"ty":"sh","ix":1,"ks":{"a":1,"k":[{"i":{"x":0.833,"y":0.833},"o":{"x":0.333,"y":0},"t":0,"s":[{"i":[[0,0],[8.348,-0.955],[0,-18.663],[0,0],[0,0],[0,12.271],[0,0],[0,0]],"o":[[-8.363,-0.004],[-18.541,2.122],[0,0],[0,0],[12.271,0],[0,0],[0,0],[0,0]],"v":[[28.76,-66.918],[3.688,-65.491],[-28.76,-28.831],[-25.521,4.483],[-19.45,66.918],[2.769,44.699],[-2.282,10.058],[-2.041,9.942]],"c":false}]},{"i":{"x":0.163,"y":1},"o":{"x":0.167,"y":0.167},"t":2,"s":[{"i":[[0,0],[8.348,-0.955],[0.13,-18.689],[0,0],[0,0],[-0.131,12.233],[0,0],[0,0]],"o":[[-8.363,-0.004],[-18.541,2.122],[0,0],[0,0],[12.233,0.131],[0,0],[0,0],[0,0]],"v":[[28.422,-66.919],[3.349,-65.492],[-29.148,-28.852],[-26.12,4.284],[-20.694,66.504],[1.693,44.592],[-3.175,4.55],[-6.879,-25.809]],"c":false}]},{"i":{"x":0.667,"y":1},"o":{"x":0.333,"y":0},"t":27,"s":[{"i":[[0,0],[8.348,-0.955],[6.55,-20.006],[0,0],[0,0],[-6.602,10.344],[0,0],[0,0]],"o":[[-8.363,-0.004],[-18.541,2.122],[0,0],[0,0],[10.344,6.602],[0,0],[0,0],[0,0]],"v":[[11.76,-66.981],[-13.312,-65.555],[-48.26,-29.894],[-55.662,-5.557],[-81.986,46.117],[-51.302,39.342],[-34.865,4.134],[-23.541,-25.872]],"c":false}]},{"i":{"x":0.833,"y":0.833},"o":{"x":0.545,"y":0},"t":68,"s":[{"i":[[0,0],[8.348,-0.955],[6.55,-20.006],[0,0],[0,0],[-6.602,10.344],[0,0],[0,0]],"o":[[-8.363,-0.004],[-18.541,2.122],[0,0],[0,0],[10.344,6.602],[0,0],[0,0],[0,0]],"v":[[11.76,-66.981],[-13.312,-65.555],[-48.26,-29.894],[-55.662,-5.557],[-81.986,46.117],[-51.302,39.342],[-34.865,4.134],[-23.541,-25.872]],"c":false}]},{"i":{"x":0.463,"y":1},"o":{"x":0.167,"y":0.167},"t":91,"s":[{"i":[[0,0],[8.348,-0.955],[0.114,-18.686],[0,0],[0,0],[-0.115,12.238],[0,0],[0,0]],"o":[[-8.363,-0.004],[-18.541,2.122],[0,0],[0,0],[12.238,0.115],[0,0],[0,0],[0,0]],"v":[[30.429,-66.696],[5.356,-65.27],[-27.136,-28.627],[-24.082,4.531],[-18.577,66.777],[3.79,44.828],[-1.131,4.773],[-4.873,-25.587]],"c":false}]},{"i":{"x":0.667,"y":1},"o":{"x":0.333,"y":0},"t":94,"s":[{"i":[[0,0],[8.348,-0.955],[0,-18.663],[0,0],[0,0],[0,12.271],[0,0],[0,0]],"o":[[-8.363,-0.004],[-18.541,2.122],[0,0],[0,0],[12.271,0],[0,0],[0,0],[0,0]],"v":[[30.76,-66.691],[5.688,-65.265],[-26.76,-28.604],[-23.521,4.71],[-17.45,67.144],[4.769,44.925],[-0.032,10.785],[-0.041,10.668]],"c":false}]},{"t":115,"s":[{"i":[[0,0],[8.348,-0.955],[0,-18.663],[0,0],[0,0],[0,12.271],[0,0],[0,0]],"o":[[-8.363,-0.004],[-18.541,2.122],[0,0],[0,0],[12.271,0],[0,0],[0,0],[0,0]],"v":[[28.76,-66.918],[3.688,-65.491],[-28.76,-28.831],[-25.521,4.483],[-19.45,66.918],[2.769,44.699],[-2.282,10.058],[-2.041,9.942]],"c":false}]}],"ix":2},"nm":"Path 1","mn":"ADBE Vector Shape - Group","hd":false},{"ty":"st","c":{"a":0,"k":[0.071,0.075,0.192,1],"ix":3,"x":"var $bm_rt;\n$bm_rt = comp('wired-lineal-653-marriage').layer('control').effect('primary')('Color');"},"o":{"a":0,"k":100,"ix":4},"w":{"a":0,"k":0,"ix":5,"x":"var $bm_rt;\n$bm_rt = $bm_mul($bm_div(value, 1), comp('wired-lineal-653-marriage').layer('control').effect('stroke')('Menu'));"},"lc":2,"lj":2,"bm":0,"nm":".primary","mn":"ADBE Vector Graphic - Stroke","hd":false,"cl":"primary"},{"ty":"fl","c":{"a":0,"k":[0.698,0.408,0.212,1],"ix":4,"x":"var $bm_rt;\n$bm_rt = comp('wired-lineal-653-marriage').layer('control').effect('quaternary')('Color');"},"o":{"a":0,"k":100,"ix":5},"r":1,"bm":0,"nm":".quaternary","mn":"ADBE Vector Graphic - Fill","hd":false,"cl":"quaternary"},{"ty":"tr","p":{"a":0,"k":[308.71,214.9],"ix":2},"a":{"a":0,"k":[0,0],"ix":1},"s":{"a":0,"k":[100,100],"ix":3},"r":{"a":0,"k":0,"ix":6},"o":{"a":0,"k":100,"ix":7},"sk":{"a":0,"k":0,"ix":4},"sa":{"a":0,"k":0,"ix":5},"nm":"Transform"}],"nm":"Group 7","np":3,"cix":2,"bm":0,"ix":1,"mn":"ADBE Vector Group","hd":false}],"ip":0,"op":844,"st":0,"ct":1,"bm":0},{"ddd":0,"ind":2,"ty":4,"nm":"Man","tt":2,"tp":1,"sr":1,"ks":{"o":{"a":0,"k":100,"ix":11},"r":{"a":0,"k":0,"ix":10},"p":{"a":0,"k":[119.643,400.509,0],"ix":2,"l":2},"a":{"a":0,"k":[154.643,435.509,0],"ix":1,"l":2},"s":{"a":0,"k":[100,100,100],"ix":6,"l":2}},"ao":0,"shapes":[{"ty":"gr","it":[{"ind":0,"ty":"sh","ix":1,"ks":{"a":1,"k":[{"i":{"x":0.163,"y":1},"o":{"x":0.333,"y":0},"t":0,"s":[{"i":[[-11.04,0],[0,0],[0,3.302],[0,0],[11.04,0],[0,0],[0,-11.04],[0,0]],"o":[[0,0],[3.302,0],[0,0],[0,-11.04],[0,0],[-11.04,0],[0,0],[0,11.04]],"v":[[-3.231,-105.345],[17.407,-105.345],[23.411,-111.349],[23.411,-144.088],[3.339,-164.16],[-3.231,-164.16],[-23.303,-144.088],[-23.303,-125.417]],"c":true}]},{"i":{"x":0.667,"y":1},"o":{"x":0.333,"y":0},"t":30,"s":[{"i":[[-11.011,0.799],[0,0],[0.239,3.293],[0,0],[11.011,-0.799],[0,0],[-0.799,-11.011],[0,0]],"o":[[0,0],[3.293,-0.239],[0,0],[-0.799,-11.011],[0,0],[-11.011,0.799],[0,0],[0.799,11.011]],"v":[[23.444,-103.994],[44.028,-105.488],[49.581,-111.91],[47.211,-144.564],[25.739,-163.131],[19.186,-162.655],[0.62,-141.183],[1.971,-122.56]],"c":true}]},{"i":{"x":0.667,"y":1},"o":{"x":0.787,"y":0},"t":68,"s":[{"i":[[-11.011,0.799],[0,0],[0.239,3.293],[0,0],[11.011,-0.799],[0,0],[-0.799,-11.011],[0,0]],"o":[[0,0],[3.293,-0.239],[0,0],[-0.799,-11.011],[0,0],[-11.011,0.799],[0,0],[0.799,11.011]],"v":[[23.444,-103.994],[44.028,-105.488],[49.581,-111.91],[47.211,-144.564],[25.739,-163.131],[19.186,-162.655],[0.62,-141.183],[1.971,-122.56]],"c":true}]},{"i":{"x":0.667,"y":1},"o":{"x":0.333,"y":0},"t":100,"s":[{"i":[[-11.04,0],[0,0],[0,3.302],[0,0],[11.04,0],[0,0],[0,-11.04],[0,0]],"o":[[0,0],[3.302,0],[0,0],[0,-11.04],[0,0],[-11.04,0],[0,0],[0,11.04]],"v":[[-5.731,-105.194],[14.907,-105.194],[20.911,-111.197],[20.911,-143.937],[0.839,-164.009],[-5.731,-164.009],[-25.803,-143.937],[-25.803,-125.266]],"c":true}]},{"t":120,"s":[{"i":[[-11.04,0],[0,0],[0,3.302],[0,0],[11.04,0],[0,0],[0,-11.04],[0,0]],"o":[[0,0],[3.302,0],[0,0],[0,-11.04],[0,0],[-11.04,0],[0,0],[0,11.04]],"v":[[-3.231,-105.345],[17.407,-105.345],[23.411,-111.349],[23.411,-144.088],[3.339,-164.16],[-3.231,-164.16],[-23.303,-144.088],[-23.303,-125.417]],"c":true}]}],"ix":2},"nm":"Path 8","mn":"ADBE Vector Shape - Group","hd":false},{"ty":"st","c":{"a":0,"k":[0.071,0.075,0.192,1],"ix":3,"x":"var $bm_rt;\n$bm_rt = comp('wired-lineal-653-marriage').layer('control').effect('primary')('Color');"},"o":{"a":0,"k":100,"ix":4},"w":{"a":0,"k":3.5,"ix":5,"x":"var $bm_rt;\n$bm_rt = $bm_mul($bm_div(value, 1), comp('wired-lineal-653-marriage').layer('control').effect('stroke')('Menu'));"},"lc":2,"lj":2,"bm":0,"nm":".primary","mn":"ADBE Vector Graphic - Stroke","hd":false,"cl":"primary"},{"ty":"tr","p":{"a":0,"k":[154.641,230.355],"ix":2},"a":{"a":0,"k":[0,0],"ix":1},"s":{"a":0,"k":[100,100],"ix":3},"r":{"a":0,"k":0,"ix":6},"o":{"a":0,"k":100,"ix":7},"sk":{"a":0,"k":0,"ix":4},"sa":{"a":0,"k":0,"ix":5},"nm":"Transform"}],"nm":"Group 8","np":2,"cix":2,"bm":0,"ix":1,"mn":"ADBE Vector Group","hd":false},{"ty":"gr","it":[{"ind":0,"ty":"sh","ix":1,"ks":{"a":1,"k":[{"i":{"x":0.162,"y":1},"o":{"x":0.333,"y":0},"t":0,"s":[{"i":[[0.135,-3.263],[6.195,3.753],[7.861,3.483],[1.679,-6.005],[-0.06,1.091],[-11.601,-0.996],[0,0],[-3.252,-7.465]],"o":[[-0.65,-1.99],[-6.803,-4.121],[-9.686,-4.292],[-0.037,-1.235],[0.598,-10.876],[0,0],[9.637,-0.519],[1.368,2.94]],"v":[[23.352,11.15],[15.688,1.614],[-5.542,6.029],[-23.356,11.15],[-23.329,7.726],[-1.577,-11.074],[1.568,-11.074],[21.78,1.217]],"c":true}]},{"i":{"x":0.667,"y":1},"o":{"x":0.333,"y":0},"t":30,"s":[{"i":[[0.135,-3.263],[6.195,3.753],[7.861,3.483],[1.679,-6.005],[-0.082,1.09],[-9.891,1.024],[0,0],[-3.252,-7.465]],"o":[[-0.65,-1.99],[-6.803,-4.121],[-9.686,-4.292],[-0.037,-1.235],[0.798,-10.651],[0,0],[9.637,-0.519],[1.368,2.94]],"v":[[47.352,11.951],[38.063,2.916],[16.833,7.33],[0.644,12.576],[0.609,9.215],[19.235,-9.647],[25.63,-10.147],[45.655,2.018]],"c":true}]},{"i":{"x":0.667,"y":1},"o":{"x":0.785,"y":0},"t":68,"s":[{"i":[[0.135,-3.263],[6.195,3.753],[7.861,3.483],[1.679,-6.005],[-0.082,1.09],[-9.891,1.024],[0,0],[-3.252,-7.465]],"o":[[-0.65,-1.99],[-6.803,-4.121],[-9.686,-4.292],[-0.037,-1.235],[0.798,-10.651],[0,0],[9.637,-0.519],[1.368,2.94]],"v":[[47.352,11.951],[38.063,2.916],[16.833,7.33],[0.644,12.576],[0.609,9.215],[19.235,-9.647],[25.63,-10.147],[45.655,2.018]],"c":true}]},{"i":{"x":0.667,"y":1},"o":{"x":0.333,"y":0},"t":100,"s":[{"i":[[0.135,-3.263],[6.195,3.753],[7.861,3.483],[1.679,-6.005],[-0.06,1.091],[-11.601,-0.996],[0,0],[-3.252,-7.465]],"o":[[-0.65,-1.99],[-6.803,-4.121],[-9.686,-4.292],[-0.037,-1.235],[0.598,-10.876],[0,0],[9.637,-0.519],[1.368,2.94]],"v":[[20.852,11.4],[15.688,1.614],[-5.542,6.029],[-25.856,11.4],[-25.829,7.976],[-4.077,-10.824],[-0.932,-10.824],[19.28,1.467]],"c":true}]},{"t":120,"s":[{"i":[[0.135,-3.263],[6.195,3.753],[7.861,3.483],[1.679,-6.005],[-0.06,1.091],[-11.601,-0.996],[0,0],[-3.252,-7.465]],"o":[[-0.65,-1.99],[-6.803,-4.121],[-9.686,-4.292],[-0.037,-1.235],[0.598,-10.876],[0,0],[9.637,-0.519],[1.368,2.94]],"v":[[23.352,11.15],[15.688,1.614],[-5.542,6.029],[-23.356,11.15],[-23.329,7.726],[-1.577,-11.074],[1.568,-11.074],[21.78,1.217]],"c":true}]}],"ix":2},"nm":"Path 1","mn":"ADBE Vector Shape - Group","hd":false},{"ty":"fl","c":{"a":0,"k":[0.835,0.624,0.502,1],"ix":4,"x":"var $bm_rt;\n$bm_rt = comp('wired-lineal-653-marriage').layer('control').effect('senary')('Color');"},"o":{"a":0,"k":50,"ix":5},"r":1,"bm":1,"nm":".senary","mn":"ADBE Vector Graphic - Fill","hd":false,"cl":"senary"},{"ty":"fl","c":{"a":0,"k":[0.835,0.624,0.502,1],"ix":4,"x":"var $bm_rt;\n$bm_rt = comp('wired-lineal-653-marriage').layer('control').effect('senary')('Color');"},"o":{"a":0,"k":100,"ix":5},"r":1,"bm":0,"nm":".senary","mn":"ADBE Vector Graphic - Fill","hd":false,"cl":"senary"},{"ty":"tr","p":{"a":0,"k":[154.656,77.311],"ix":2},"a":{"a":0,"k":[0,0],"ix":1},"s":{"a":0,"k":[100,100],"ix":3},"r":{"a":0,"k":0,"ix":6},"o":{"a":0,"k":100,"ix":7},"sk":{"a":0,"k":0,"ix":4},"sa":{"a":0,"k":0,"ix":5},"nm":"Transform"}],"nm":"Group 7","np":3,"cix":2,"bm":0,"ix":2,"mn":"ADBE Vector Group","hd":false},{"ty":"gr","it":[{"ind":0,"ty":"sh","ix":1,"ks":{"a":1,"k":[{"i":{"x":0.163,"y":1},"o":{"x":0.333,"y":0},"t":0,"s":[{"i":[[-11.04,0],[0,0],[0,3.302],[0,0],[11.04,0],[0,0],[0,-11.04],[0,0]],"o":[[0,0],[3.302,0],[0,0],[0,-11.04],[0,0],[-11.04,0],[0,0],[0,11.04]],"v":[[-3.231,-105.345],[17.407,-105.345],[23.411,-111.349],[23.411,-144.088],[3.339,-164.16],[-3.231,-164.16],[-23.303,-144.088],[-23.303,-125.417]],"c":true}]},{"i":{"x":0.667,"y":1},"o":{"x":0.333,"y":0},"t":30,"s":[{"i":[[-11.011,0.799],[0,0],[0.239,3.293],[0,0],[11.011,-0.799],[0,0],[-0.799,-11.011],[0,0]],"o":[[0,0],[3.293,-0.239],[0,0],[-0.799,-11.011],[0,0],[-11.011,0.799],[0,0],[0.799,11.011]],"v":[[23.444,-103.994],[44.028,-105.488],[49.581,-111.91],[47.211,-144.564],[25.739,-163.131],[19.186,-162.655],[0.62,-141.183],[1.971,-122.56]],"c":true}]},{"i":{"x":0.667,"y":1},"o":{"x":0.787,"y":0},"t":68,"s":[{"i":[[-11.011,0.799],[0,0],[0.239,3.293],[0,0],[11.011,-0.799],[0,0],[-0.799,-11.011],[0,0]],"o":[[0,0],[3.293,-0.239],[0,0],[-0.799,-11.011],[0,0],[-11.011,0.799],[0,0],[0.799,11.011]],"v":[[23.444,-103.994],[44.028,-105.488],[49.581,-111.91],[47.211,-144.564],[25.739,-163.131],[19.186,-162.655],[0.62,-141.183],[1.971,-122.56]],"c":true}]},{"i":{"x":0.667,"y":1},"o":{"x":0.333,"y":0},"t":100,"s":[{"i":[[-11.04,0],[0,0],[0,3.302],[0,0],[11.04,0],[0,0],[0,-11.04],[0,0]],"o":[[0,0],[3.302,0],[0,0],[0,-11.04],[0,0],[-11.04,0],[0,0],[0,11.04]],"v":[[-5.731,-105.194],[14.907,-105.194],[20.911,-111.197],[20.911,-143.937],[0.839,-164.009],[-5.731,-164.009],[-25.803,-143.937],[-25.803,-125.266]],"c":true}]},{"t":120,"s":[{"i":[[-11.04,0],[0,0],[0,3.302],[0,0],[11.04,0],[0,0],[0,-11.04],[0,0]],"o":[[0,0],[3.302,0],[0,0],[0,-11.04],[0,0],[-11.04,0],[0,0],[0,11.04]],"v":[[-3.231,-105.345],[17.407,-105.345],[23.411,-111.349],[23.411,-144.088],[3.339,-164.16],[-3.231,-164.16],[-23.303,-144.088],[-23.303,-125.417]],"c":true}]}],"ix":2},"nm":"Path 8","mn":"ADBE Vector Shape - Group","hd":false},{"ty":"fl","c":{"a":0,"k":[0.976,0.788,0.753,1],"ix":4,"x":"var $bm_rt;\n$bm_rt = comp('wired-lineal-653-marriage').layer('control').effect('septenary')('Color');"},"o":{"a":0,"k":100,"ix":5},"r":1,"bm":0,"nm":".septenary","mn":"ADBE Vector Graphic - Fill","hd":false,"cl":"septenary"},{"ty":"tr","p":{"a":0,"k":[154.641,230.355],"ix":2},"a":{"a":0,"k":[0,0],"ix":1},"s":{"a":0,"k":[100,100],"ix":3},"r":{"a":0,"k":0,"ix":6},"o":{"a":0,"k":100,"ix":7},"sk":{"a":0,"k":0,"ix":4},"sa":{"a":0,"k":0,"ix":5},"nm":"Transform"}],"nm":"Group 6","np":2,"cix":2,"bm":0,"ix":3,"mn":"ADBE Vector Group","hd":false},{"ty":"gr","it":[{"ind":0,"ty":"sh","ix":1,"ks":{"a":1,"k":[{"i":{"x":0.163,"y":1},"o":{"x":0.333,"y":0},"t":0,"s":[{"i":[[0,0],[0,0]],"o":[[0,0],[0,0]],"v":[[0,-23.683],[0,23.683]],"c":false}]},{"i":{"x":0.667,"y":1},"o":{"x":0.333,"y":0},"t":30,"s":[{"i":[[0,0],[0,0]],"o":[[0,0],[0,0]],"v":[[34.373,-31.004],[33.609,23.359]],"c":false}]},{"i":{"x":0.667,"y":1},"o":{"x":0.787,"y":0},"t":68,"s":[{"i":[[0,0],[0,0]],"o":[[0,0],[0,0]],"v":[[34.373,-31.004],[33.609,23.359]],"c":false}]},{"i":{"x":0.667,"y":1},"o":{"x":0.333,"y":0},"t":100,"s":[{"i":[[0,0],[0,0]],"o":[[0,0],[0,0]],"v":[[-5,-23.697],[-5,23.669]],"c":false}]},{"t":120,"s":[{"i":[[0,0],[0,0]],"o":[[0,0],[0,0]],"v":[[0,-23.683],[0,23.683]],"c":false}]}],"ix":2},"nm":"Path 1","mn":"ADBE Vector Shape - Group","hd":false},{"ind":1,"ty":"sh","ix":2,"ks":{"a":1,"k":[{"i":{"x":0.163,"y":1},"o":{"x":0.333,"y":0},"t":0,"s":[{"i":[[0,0],[0,0]],"o":[[0,0],[0,0]],"v":[[39.599,23.683],[-39.595,23.683]],"c":false}]},{"i":{"x":0.667,"y":1},"o":{"x":0.333,"y":0},"t":30,"s":[{"i":[[0,0],[0,0]],"o":[[0,0],[0,0]],"v":[[52.705,23.844],[-26.483,22.878]],"c":false}]},{"i":{"x":0.667,"y":1},"o":{"x":0.787,"y":0},"t":68,"s":[{"i":[[0,0],[0,0]],"o":[[0,0],[0,0]],"v":[[52.705,23.844],[-26.483,22.878]],"c":false}]},{"i":{"x":0.667,"y":1},"o":{"x":0.333,"y":0},"t":100,"s":[{"i":[[0,0],[0,0]],"o":[[0,0],[0,0]],"v":[[37.099,23.835],[-42.095,23.835]],"c":false}]},{"t":120,"s":[{"i":[[0,0],[0,0]],"o":[[0,0],[0,0]],"v":[[39.599,23.683],[-39.595,23.683]],"c":false}]}],"ix":2},"nm":"Path 2","mn":"ADBE Vector Shape - Group","hd":false},{"ind":2,"ty":"sh","ix":3,"ks":{"a":1,"k":[{"i":{"x":0.163,"y":1},"o":{"x":0.333,"y":0},"t":0,"s":[{"i":[[0,0],[0,0],[0,0]],"o":[[0,0],[0,0],[0,0]],"v":[[-24.763,-81.429],[0,-23.683],[24.763,-81.429]],"c":false}]},{"i":{"x":0.667,"y":1},"o":{"x":0.333,"y":0},"t":30,"s":[{"i":[[0,0],[0,0],[0,0]],"o":[[0,0],[0,0],[0,0]],"v":[[-10.37,-82.045],[34.373,-31.004],[39.152,-81.441]],"c":false}]},{"i":{"x":0.667,"y":1},"o":{"x":0.787,"y":0},"t":68,"s":[{"i":[[0,0],[0,0],[0,0]],"o":[[0,0],[0,0],[0,0]],"v":[[-10.37,-82.045],[34.373,-31.004],[39.152,-81.441]],"c":false}]},{"i":{"x":0.667,"y":1},"o":{"x":0.333,"y":0},"t":100,"s":[{"i":[[0,0],[0,0],[0,0]],"o":[[0,0],[0,0],[0,0]],"v":[[-27.263,-81.277],[-5,-23.697],[22.263,-81.277]],"c":false}]},{"t":120,"s":[{"i":[[0,0],[0,0],[0,0]],"o":[[0,0],[0,0],[0,0]],"v":[[-24.763,-81.429],[0,-23.683],[24.763,-81.429]],"c":false}]}],"ix":2},"nm":"Path 3","mn":"ADBE Vector Shape - Group","hd":false},{"ind":3,"ty":"sh","ix":4,"ks":{"a":1,"k":[{"i":{"x":0.163,"y":1},"o":{"x":0.333,"y":0},"t":0,"s":[{"i":[[0,0],[-11.208,-1.306],[0,-18.584],[0,0],[0,0],[0,29.101],[0,0],[0,0]],"o":[[11.236,-0.005],[18.459,2.151],[0,0],[0,0],[0,0],[0,0],[0,0],[0,0]],"v":[[0.002,-82.497],[33.681,-80.544],[65.987,-44.029],[65.987,-9.555],[65.987,50.811],[39.599,24.847],[39.599,-5.609],[39.599,-41.549]],"c":false}]},{"i":{"x":0.667,"y":1},"o":{"x":0.333,"y":0},"t":30,"s":[{"i":[[0,0],[-11.191,-1.443],[0.227,-18.582],[0,0],[0,0],[8.071,27.959],[0,0],[0,0]],"o":[[11.235,0.132],[18.431,2.376],[0,0],[0,0],[0,0],[0,0],[0,0],[0,0]],"v":[[14.406,-82.811],[48.059,-80.448],[79.917,-43.541],[78.76,-15.063],[98.334,35.884],[65.779,18.257],[56.486,-2.028],[53.5,-41.383]],"c":false}]},{"i":{"x":0.667,"y":1},"o":{"x":0.787,"y":0},"t":68,"s":[{"i":[[0,0],[-11.191,-1.443],[0.227,-18.582],[0,0],[0,0],[8.071,27.959],[0,0],[0,0]],"o":[[11.235,0.132],[18.431,2.376],[0,0],[0,0],[0,0],[0,0],[0,0],[0,0]],"v":[[14.406,-82.811],[48.059,-80.448],[79.917,-43.541],[78.76,-15.063],[98.334,35.884],[65.779,18.257],[56.486,-2.028],[53.5,-41.383]],"c":false}]},{"i":{"x":0.667,"y":1},"o":{"x":0.333,"y":0},"t":100,"s":[{"i":[[0,0],[-11.208,-1.306],[0,-18.584],[0,0],[0,0],[0,29.101],[0,0],[0,0]],"o":[[11.236,-0.005],[18.459,2.151],[0,0],[0,0],[0,0],[0,0],[0,0],[0,0]],"v":[[-2.498,-82.345],[31.181,-80.393],[63.487,-43.878],[63.487,-9.404],[63.487,50.963],[37.099,24.998],[37.099,-5.457],[37.099,-41.398]],"c":false}]},{"t":120,"s":[{"i":[[0,0],[-11.208,-1.306],[0,-18.584],[0,0],[0,0],[0,29.101],[0,0],[0,0]],"o":[[11.236,-0.005],[18.459,2.151],[0,0],[0,0],[0,0],[0,0],[0,0],[0,0]],"v":[[0.002,-82.497],[33.681,-80.544],[65.987,-44.029],[65.987,-9.555],[65.987,50.811],[39.599,24.847],[39.599,-5.609],[39.599,-41.549]],"c":false}]}],"ix":2},"nm":"Path 4","mn":"ADBE Vector Shape - Group","hd":false},{"ind":4,"ty":"sh","ix":5,"ks":{"a":1,"k":[{"i":{"x":0.163,"y":1},"o":{"x":0.333,"y":0},"t":0,"s":[{"i":[[0,0],[11.208,-1.306],[0,-18.583],[0,0],[0,29.101],[0,0]],"o":[[-11.236,-0.005],[-18.458,2.151],[0,0],[0,0],[0,0],[0,0]],"v":[[0.002,-82.497],[-33.678,-80.544],[-65.983,-44.029],[-65.983,50.811],[-39.595,24.847],[-39.595,-41.549]],"c":false}]},{"i":{"x":0.667,"y":1},"o":{"x":0.333,"y":0},"t":30,"s":[{"i":[[0,0],[11.223,-1.17],[0.227,-18.582],[0,0],[-0.355,29.099],[0,0]],"o":[[-11.235,-0.142],[-18.483,1.926],[0,0],[0,0],[0,0],[0,0]],"v":[[14.406,-82.811],[-19.296,-81.27],[-52.044,-45.151],[-53.2,49.682],[-26.497,24.042],[-25.688,-42.349]],"c":false}]},{"i":{"x":0.667,"y":1},"o":{"x":0.787,"y":0},"t":68,"s":[{"i":[[0,0],[11.223,-1.17],[0.227,-18.582],[0,0],[-0.355,29.099],[0,0]],"o":[[-11.235,-0.142],[-18.483,1.926],[0,0],[0,0],[0,0],[0,0]],"v":[[14.406,-82.811],[-19.296,-81.27],[-52.044,-45.151],[-53.2,49.682],[-26.497,24.042],[-25.688,-42.349]],"c":false}]},{"i":{"x":0.667,"y":1},"o":{"x":0.333,"y":0},"t":100,"s":[{"i":[[0,0],[11.208,-1.306],[0,-18.583],[0,0],[0,29.101],[0,0]],"o":[[-11.236,-0.005],[-18.458,2.151],[0,0],[0,0],[0,0],[0,0]],"v":[[-2.498,-82.345],[-36.178,-80.393],[-68.483,-43.878],[-68.483,50.963],[-42.095,24.998],[-42.095,-41.398]],"c":false}]},{"t":120,"s":[{"i":[[0,0],[11.208,-1.306],[0,-18.583],[0,0],[0,29.101],[0,0]],"o":[[-11.236,-0.005],[-18.458,2.151],[0,0],[0,0],[0,0],[0,0]],"v":[[0.002,-82.497],[-33.678,-80.544],[-65.983,-44.029],[-65.983,50.811],[-39.595,24.847],[-39.595,-41.549]],"c":false}]}],"ix":2},"nm":"Path 5","mn":"ADBE Vector Shape - Group","hd":false},{"ind":5,"ty":"sh","ix":6,"ks":{"a":1,"k":[{"i":{"x":0.163,"y":1},"o":{"x":0.333,"y":0},"t":0,"s":[{"i":[[0,0],[0,0]],"o":[[0,0],[0,0]],"v":[[-39.595,-41.549],[-39.557,27.636]],"c":false}]},{"i":{"x":0.667,"y":1},"o":{"x":0.333,"y":0},"t":30,"s":[{"i":[[0,0],[0,0]],"o":[[0,0],[0,0]],"v":[[-25.688,-42.349],[-26.493,26.831]],"c":false}]},{"i":{"x":0.667,"y":1},"o":{"x":0.787,"y":0},"t":68,"s":[{"i":[[0,0],[0,0]],"o":[[0,0],[0,0]],"v":[[-25.688,-42.349],[-26.493,26.831]],"c":false}]},{"i":{"x":0.667,"y":1},"o":{"x":0.333,"y":0},"t":100,"s":[{"i":[[0,0],[0,0]],"o":[[0,0],[0,0]],"v":[[-42.095,-41.398],[-42.057,27.788]],"c":false}]},{"t":120,"s":[{"i":[[0,0],[0,0]],"o":[[0,0],[0,0]],"v":[[-39.595,-41.549],[-39.557,27.636]],"c":false}]}],"ix":2},"nm":"Path 6","mn":"ADBE Vector Shape - Group","hd":false},{"ind":6,"ty":"sh","ix":7,"ks":{"a":1,"k":[{"i":{"x":0.163,"y":1},"o":{"x":0.333,"y":0},"t":0,"s":[{"i":[[0,0],[0,0]],"o":[[0,0],[0,0]],"v":[[39.571,27.636],[39.571,-41.549]],"c":false}]},{"i":{"x":0.667,"y":1},"o":{"x":0.333,"y":0},"t":30,"s":[{"i":[[0,0],[0,0]],"o":[[0,0],[0,0]],"v":[[52.629,27.796],[53.472,-41.384]],"c":false}]},{"i":{"x":0.667,"y":1},"o":{"x":0.787,"y":0},"t":68,"s":[{"i":[[0,0],[0,0]],"o":[[0,0],[0,0]],"v":[[52.629,27.796],[53.472,-41.384]],"c":false}]},{"i":{"x":0.667,"y":1},"o":{"x":0.333,"y":0},"t":100,"s":[{"i":[[0,0],[0,0]],"o":[[0,0],[0,0]],"v":[[37.071,27.788],[37.071,-41.398]],"c":false}]},{"t":120,"s":[{"i":[[0,0],[0,0]],"o":[[0,0],[0,0]],"v":[[39.571,27.636],[39.571,-41.549]],"c":false}]}],"ix":2},"nm":"Path 7","mn":"ADBE Vector Shape - Group","hd":false},{"ind":7,"ty":"sh","ix":8,"ks":{"a":1,"k":[{"i":{"x":0.163,"y":1},"o":{"x":0.333,"y":0},"t":0,"s":[{"i":[[0,0],[0,0],[-8.769,0],[0,0],[0,0]],"o":[[0,0],[0,0],[8.262,-13.046],[0,0],[0,0]],"v":[[0.002,65.376],[0.023,208.154],[53.789,208.154],[36.376,182.522],[39.568,27.636]],"c":false}]},{"i":{"x":0.667,"y":1},"o":{"x":0.333,"y":0},"t":30,"s":[{"i":[[0,0],[0,0],[-8.769,0],[0,0],[0,0]],"o":[[0,0],[0,0],[8.262,-13.046],[0,0],[0,0]],"v":[[12.602,65.051],[0.023,208.154],[53.789,208.154],[36.376,182.522],[52.626,27.796]],"c":false}]},{"i":{"x":0.667,"y":1},"o":{"x":0.787,"y":0},"t":68,"s":[{"i":[[0,0],[0,0],[-8.769,0],[0,0],[0,0]],"o":[[0,0],[0,0],[8.262,-13.046],[0,0],[0,0]],"v":[[12.602,65.051],[0.023,208.154],[53.789,208.154],[36.376,182.522],[52.626,27.796]],"c":false}]},{"i":{"x":0.667,"y":1},"o":{"x":0.333,"y":0},"t":100,"s":[{"i":[[0,0],[0,0],[-8.769,0],[0,0],[0,0]],"o":[[0,0],[0,0],[8.262,-13.046],[0,0],[0,0]],"v":[[-2.498,65.527],[0.023,208.154],[53.789,208.154],[36.376,182.522],[37.068,27.788]],"c":false}]},{"t":120,"s":[{"i":[[0,0],[0,0],[-8.769,0],[0,0],[0,0]],"o":[[0,0],[0,0],[8.262,-13.046],[0,0],[0,0]],"v":[[0.002,65.376],[0.023,208.154],[53.789,208.154],[36.376,182.522],[39.568,27.636]],"c":false}]}],"ix":2},"nm":"Path 9","mn":"ADBE Vector Shape - Group","hd":false},{"ind":8,"ty":"sh","ix":9,"ks":{"a":1,"k":[{"i":{"x":0.163,"y":1},"o":{"x":0.333,"y":0},"t":0,"s":[{"i":[[0,0],[0,0],[8.769,0],[0,0],[0,0]],"o":[[0,0],[0,0],[-8.262,-13.046],[0,0],[0,0]],"v":[[-0.012,65.376],[-0.033,208.154],[-53.799,208.154],[-36.386,182.522],[-39.578,27.636]],"c":false}]},{"i":{"x":0.667,"y":1},"o":{"x":0.333,"y":0},"t":30,"s":[{"i":[[0,0],[0,0],[8.769,0],[0,0],[0,0]],"o":[[0,0],[0,0],[-8.262,-13.046],[0,0],[0,0]],"v":[[12.589,65.05],[-0.033,208.154],[-53.799,208.154],[-36.386,182.522],[-26.514,26.831]],"c":false}]},{"i":{"x":0.667,"y":1},"o":{"x":0.787,"y":0},"t":68,"s":[{"i":[[0,0],[0,0],[8.769,0],[0,0],[0,0]],"o":[[0,0],[0,0],[-8.262,-13.046],[0,0],[0,0]],"v":[[12.589,65.05],[-0.033,208.154],[-53.799,208.154],[-36.386,182.522],[-26.514,26.831]],"c":false}]},{"i":{"x":0.667,"y":1},"o":{"x":0.333,"y":0},"t":100,"s":[{"i":[[0,0],[0,0],[8.769,0],[0,0],[0,0]],"o":[[0,0],[0,0],[-8.262,-13.046],[0,0],[0,0]],"v":[[-2.512,65.527],[-0.033,208.154],[-53.799,208.154],[-36.386,182.522],[-42.078,27.788]],"c":false}]},{"t":120,"s":[{"i":[[0,0],[0,0],[8.769,0],[0,0],[0,0]],"o":[[0,0],[0,0],[-8.262,-13.046],[0,0],[0,0]],"v":[[-0.012,65.376],[-0.033,208.154],[-53.799,208.154],[-36.386,182.522],[-39.578,27.636]],"c":false}]}],"ix":2},"nm":"Path 10","mn":"ADBE Vector Shape - Group","hd":false},{"ty":"st","c":{"a":0,"k":[0.071,0.075,0.192,1],"ix":3,"x":"var $bm_rt;\n$bm_rt = comp('wired-lineal-653-marriage').layer('control').effect('primary')('Color');"},"o":{"a":0,"k":100,"ix":4},"w":{"a":0,"k":3.5,"ix":5,"x":"var $bm_rt;\n$bm_rt = $bm_mul($bm_div(value, 1), comp('wired-lineal-653-marriage').layer('control').effect('stroke')('Menu'));"},"lc":2,"lj":2,"bm":0,"nm":".primary","mn":"ADBE Vector Graphic - Stroke","hd":false,"cl":"primary"},{"ty":"tr","p":{"a":0,"k":[154.641,227.355],"ix":2},"a":{"a":0,"k":[0,0],"ix":1},"s":{"a":0,"k":[100,100],"ix":3},"r":{"a":0,"k":0,"ix":6},"o":{"a":0,"k":100,"ix":7},"sk":{"a":0,"k":0,"ix":4},"sa":{"a":0,"k":0,"ix":5},"nm":"Transform"}],"nm":"Group 1","np":10,"cix":2,"bm":0,"ix":4,"mn":"ADBE Vector Group","hd":false},{"ty":"gr","it":[{"ind":0,"ty":"sh","ix":1,"ks":{"a":0,"k":{"i":[[0,0],[0,0],[8.26,-13.05],[0,0]],"o":[[0,0],[0,0],[0,0],[0,0]],"v":[[-27.729,-12.82],[8.671,-12.82],[26.091,12.82],[-27.729,12.82]],"c":false},"ix":2},"nm":"Path 1","mn":"ADBE Vector Shape - Group","hd":false},{"ty":"fl","c":{"a":0,"k":[0.392,0.431,0.471,1],"ix":4,"x":"var $bm_rt;\n$bm_rt = comp('wired-lineal-653-marriage').layer('control').effect('quinary')('Color');"},"o":{"a":0,"k":100,"ix":5},"r":1,"bm":0,"nm":".quinary","mn":"ADBE Vector Graphic - Fill","hd":false,"cl":"quinary"},{"ty":"tr","p":{"a":0,"k":[182.342,422.692],"ix":2},"a":{"a":0,"k":[0,0],"ix":1},"s":{"a":0,"k":[100,100],"ix":3},"r":{"a":0,"k":0,"ix":6},"o":{"a":0,"k":100,"ix":7},"sk":{"a":0,"k":0,"ix":4},"sa":{"a":0,"k":0,"ix":5},"nm":"Transform"}],"nm":"Group 2","np":2,"cix":2,"bm":0,"ix":5,"mn":"ADBE Vector Group","hd":false},{"ty":"gr","it":[{"ind":0,"ty":"sh","ix":1,"ks":{"a":1,"k":[{"i":{"x":0.667,"y":1},"o":{"x":0.333,"y":0},"t":0,"s":[{"i":[[0,0],[0,0],[0,0],[0,0]],"o":[[0,0],[-8.26,-13.05],[0,0],[0,0]],"v":[[27.704,12.82],[-26.066,12.82],[-8.656,-12.82],[27.704,-12.82]],"c":false}]},{"i":{"x":0.667,"y":1},"o":{"x":0.333,"y":0},"t":30,"s":[{"i":[[0,0],[0,0],[0,0],[0,0]],"o":[[0,0],[-8.26,-13.05],[0,0],[0,0]],"v":[[27.704,12.82],[-26.066,12.82],[-8.656,-12.82],[30.204,-12.89]],"c":false}]},{"i":{"x":0.667,"y":1},"o":{"x":0.333,"y":0},"t":68,"s":[{"i":[[0,0],[0,0],[0,0],[0,0]],"o":[[0,0],[-8.26,-13.05],[0,0],[0,0]],"v":[[27.704,12.82],[-26.066,12.82],[-8.656,-12.82],[30.204,-12.89]],"c":false}]},{"i":{"x":0.667,"y":1},"o":{"x":0.333,"y":0},"t":100,"s":[{"i":[[0,0],[0,0],[0,0],[0,0]],"o":[[0,0],[-8.26,-13.05],[0,0],[0,0]],"v":[[27.704,12.82],[-26.066,12.82],[-8.656,-12.82],[27.329,-12.904]],"c":false}]},{"t":120,"s":[{"i":[[0,0],[0,0],[0,0],[0,0]],"o":[[0,0],[-8.26,-13.05],[0,0],[0,0]],"v":[[27.704,12.82],[-26.066,12.82],[-8.656,-12.82],[27.829,-12.934]],"c":false}]}],"ix":2},"nm":"Path 1","mn":"ADBE Vector Shape - Group","hd":false},{"ty":"fl","c":{"a":0,"k":[0.392,0.431,0.471,1],"ix":4,"x":"var $bm_rt;\n$bm_rt = comp('wired-lineal-653-marriage').layer('control').effect('quinary')('Color');"},"o":{"a":0,"k":100,"ix":5},"r":1,"bm":0,"nm":".quinary","mn":"ADBE Vector Graphic - Fill","hd":false,"cl":"quinary"},{"ty":"tr","p":{"a":0,"k":[126.91,422.692],"ix":2},"a":{"a":0,"k":[0,0],"ix":1},"s":{"a":0,"k":[100,100],"ix":3},"r":{"a":0,"k":0,"ix":6},"o":{"a":0,"k":100,"ix":7},"sk":{"a":0,"k":0,"ix":4},"sa":{"a":0,"k":0,"ix":5},"nm":"Transform"}],"nm":"Group 3","np":2,"cix":2,"bm":0,"ix":6,"mn":"ADBE Vector Group","hd":false},{"ty":"gr","it":[{"ind":0,"ty":"sh","ix":1,"ks":{"a":1,"k":[{"i":{"x":0.165,"y":1},"o":{"x":0.333,"y":0},"t":0,"s":[{"i":[[16.94,2.149],[3.864,0.33],[0,0],[0,0],[0,0],[0,0],[0,0],[3.854,-0.488],[0,-17.078],[0,0],[0,29.073],[0,0],[0,0],[0,0],[0,0],[-7.036,-0.556],[0,1.744],[0,0],[0,0]],"o":[[-3.858,-0.49],[0.034,0.011],[0,0],[0,0],[0,0],[0,0],[0,0],[-16.943,2.144],[0,0],[0.05,0.004],[0,0],[0,0],[0,0],[0,0],[0,22.756],[1.739,0.137],[0,0],[0,0],[0,-17.076]],"v":[[36.295,-64.985],[24.709,-66.205],[24.761,-66.188],[13.939,-40.963],[-0.002,-8.443],[-13.954,-40.963],[-24.765,-66.188],[-36.288,-64.986],[-65.985,-31.445],[-65.985,66.052],[-39.597,38.924],[39.62,38.345],[39.449,-26.326],[39.449,8.674],[39.597,38.924],[62.769,65.991],[65.985,62.997],[65.985,4.138],[65.985,-31.444]],"c":true}]},{"i":{"x":0.667,"y":1},"o":{"x":0.333,"y":0},"t":30,"s":[{"i":[[11.45,6.38],[2.865,0.469],[0,0],[0,0],[0,0],[0,0],[0,0],[3.86,-0.442],[0,-17.078],[0,0],[0,29.073],[0,0],[0,0],[0,0],[0,0],[0,0],[0,0],[0,0],[0,0]],"o":[[-2.47,-1.377],[0.034,0.011],[0,0],[0,0],[0,0],[0,0],[0,0],[-19.638,2.25],[0,0],[0.05,0.004],[0,0],[0,0],[0,0],[0,0],[8.477,28.464],[0,0],[0,0],[0,0],[0.089,-17.792]],"v":[[59.045,-62.61],[48.209,-65.705],[39.261,-66.688],[37.189,-43.463],[34.748,-15.693],[10.296,-43.713],[-10.14,-67.188],[-19.038,-66.736],[-51.985,-30.445],[-52.735,64.552],[-26.347,37.424],[52.87,38.314],[53.199,-26.576],[56.574,12.924],[65.847,32.924],[98.519,50.491],[95.86,44.372],[78.735,-0.112],[79.985,-28.569]],"c":true}]},{"i":{"x":0.653,"y":1},"o":{"x":0.782,"y":0},"t":68,"s":[{"i":[[11.45,6.38],[2.865,0.469],[0,0],[0,0],[0,0],[0,0],[0,0],[3.86,-0.442],[0,-17.078],[0,0],[0,29.073],[0,0],[0,0],[0,0],[0,0],[0,0],[0,0],[0,0],[0,0]],"o":[[-2.47,-1.377],[0.034,0.011],[0,0],[0,0],[0,0],[0,0],[0,0],[-19.638,2.25],[0,0],[0.05,0.004],[0,0],[0,0],[0,0],[0,0],[8.477,28.464],[0,0],[0,0],[0,0],[0.089,-17.792]],"v":[[59.045,-62.61],[48.209,-65.705],[39.261,-66.688],[37.189,-43.463],[34.748,-15.693],[10.296,-43.713],[-10.14,-67.188],[-19.038,-66.736],[-51.985,-30.445],[-52.735,64.552],[-26.347,37.424],[52.87,38.314],[53.199,-26.576],[56.574,12.924],[65.847,32.924],[98.519,50.491],[95.86,44.372],[78.735,-0.112],[79.985,-28.569]],"c":true}]},{"i":{"x":0.667,"y":1},"o":{"x":0.333,"y":0},"t":100,"s":[{"i":[[15.217,1.873],[3.864,0.33],[0,0],[0,0],[0,0],[0,0],[0,0],[3.854,-0.488],[0.747,-15.167],[0,0],[0,29.073],[0,0],[0,0],[0,0],[0,0],[0,0],[0,0],[0,0],[0,0]],"o":[[-3.86,-0.475],[0.034,0.011],[0,0],[0,0],[0,0],[0,0],[0,0],[-16.943,2.144],[0,0],[0.05,0.004],[0,0],[0,0],[0,0],[0,0],[0.165,30.464],[0,0],[0,0],[0,0],[0.026,-16.417]],"v":[[33.732,-64.985],[22.147,-66.205],[22.198,-66.188],[9.876,-39.963],[-5.064,-8.443],[-17.017,-40.463],[-27.327,-66.188],[-38.85,-64.986],[-68.548,-31.445],[-68.548,66.052],[-42.159,38.924],[37.057,38.345],[36.887,-26.326],[36.887,8.674],[37.034,38.924],[63.538,65.732],[63.47,59.372],[63.423,4.138],[63.423,-31.444]],"c":true}]},{"t":120,"s":[{"i":[[16.94,2.149],[3.864,0.33],[0,0],[0,0],[0,0],[0,0],[0,0],[3.854,-0.488],[0,-17.078],[0,0],[0,29.073],[0,0],[0,0],[0,0],[0,0],[-7.036,-0.556],[0,1.744],[0,0],[0,0]],"o":[[-3.858,-0.49],[0.034,0.011],[0,0],[0,0],[0,0],[0,0],[0,0],[-16.943,2.144],[0,0],[0.05,0.004],[0,0],[0,0],[0,0],[0,0],[0,22.756],[1.739,0.137],[0,0],[0,0],[0,-17.076]],"v":[[36.295,-64.985],[24.709,-66.205],[24.761,-66.188],[13.939,-40.963],[-0.002,-8.443],[-13.954,-40.963],[-24.765,-66.188],[-36.288,-64.986],[-65.985,-31.445],[-65.985,66.052],[-39.597,38.924],[39.62,38.345],[39.449,-26.326],[39.449,8.674],[39.597,38.924],[62.769,65.991],[65.985,62.997],[65.985,4.138],[65.985,-31.444]],"c":true}]}],"ix":2},"nm":"Path 1","mn":"ADBE Vector Shape - Group","hd":false},{"ty":"fl","c":{"a":0,"k":[0.227,0.2,0.278,1],"ix":4,"x":"var $bm_rt;\n$bm_rt = comp('wired-lineal-653-marriage').layer('control').effect('secondary')('Color');"},"o":{"a":0,"k":100,"ix":5},"r":1,"bm":0,"nm":".secondary","mn":"ADBE Vector Graphic - Fill","hd":false,"cl":"secondary"},{"ty":"tr","p":{"a":0,"k":[154.551,212.612],"ix":2},"a":{"a":0,"k":[0,0],"ix":1},"s":{"a":0,"k":[100,100],"ix":3},"r":{"a":0,"k":0,"ix":6},"o":{"a":0,"k":100,"ix":7},"sk":{"a":0,"k":0,"ix":4},"sa":{"a":0,"k":0,"ix":5},"nm":"Transform"}],"nm":"Group 5","np":2,"cix":2,"bm":0,"ix":7,"mn":"ADBE Vector Group","hd":false},{"ty":"gr","it":[{"ind":0,"ty":"sh","ix":1,"ks":{"a":1,"k":[{"i":{"x":0.165,"y":1},"o":{"x":0.333,"y":0},"t":0,"s":[{"i":[[0,0],[0,0],[0,0],[0,0],[0,0]],"o":[[0,0],[0,0],[0,0],[0,0],[0,0]],"v":[[1.926,-30.691],[-1.82,-30.691],[-6.951,16.715],[-0.011,30.691],[6.951,16.657]],"c":true}]},{"i":{"x":0.667,"y":1},"o":{"x":0.333,"y":0},"t":30,"s":[{"i":[[0,0],[0,0],[0,0],[0,0],[0,0]],"o":[[0,0],[0,0],[0,0],[0,0],[0,0]],"v":[[16.426,-30.726],[12.68,-30.726],[27.549,16.181],[34.489,30.157],[41.451,16.122]],"c":true}]},{"i":{"x":0.667,"y":1},"o":{"x":0.794,"y":0},"t":68,"s":[{"i":[[0,0],[0,0],[0,0],[0,0],[0,0]],"o":[[0,0],[0,0],[0,0],[0,0],[0,0]],"v":[[16.426,-30.726],[12.68,-30.726],[27.549,16.181],[34.489,30.157],[41.451,16.122]],"c":true}]},{"i":{"x":0.667,"y":1},"o":{"x":0.333,"y":0},"t":100,"s":[{"i":[[0,0],[0,0],[0,0],[0,0],[0,0]],"o":[[0,0],[0,0],[0,0],[0,0],[0,0]],"v":[[-0.824,-30.441],[-4.57,-30.441],[-11.951,16.965],[-5.011,30.941],[1.951,16.907]],"c":true}]},{"t":120,"s":[{"i":[[0,0],[0,0],[0,0],[0,0],[0,0]],"o":[[0,0],[0,0],[0,0],[0,0],[0,0]],"v":[[1.926,-30.691],[-1.82,-30.691],[-6.951,16.715],[-0.011,30.691],[6.951,16.657]],"c":true}]}],"ix":2},"nm":"Path 1","mn":"ADBE Vector Shape - Group","hd":false},{"ty":"fl","c":{"a":0,"k":[0.227,0.2,0.278,1],"ix":4,"x":"var $bm_rt;\n$bm_rt = comp('wired-lineal-653-marriage').layer('control').effect('secondary')('Color');"},"o":{"a":0,"k":50,"ix":5},"r":1,"bm":1,"nm":".secondary","mn":"ADBE Vector Graphic - Fill","hd":false,"cl":"secondary"},{"ty":"fl","c":{"a":0,"k":[0.227,0.2,0.278,1],"ix":4,"x":"var $bm_rt;\n$bm_rt = comp('wired-lineal-653-marriage').layer('control').effect('secondary')('Color');"},"o":{"a":0,"k":100,"ix":5},"r":1,"bm":0,"nm":".secondary","mn":"ADBE Vector Graphic - Fill","hd":false,"cl":"secondary"},{"ty":"tr","p":{"a":0,"k":[154.596,175.595],"ix":2},"a":{"a":0,"k":[0,0],"ix":1},"s":{"a":0,"k":[100,100],"ix":3},"r":{"a":0,"k":0,"ix":6},"o":{"a":0,"k":100,"ix":7},"sk":{"a":0,"k":0,"ix":4},"sa":{"a":0,"k":0,"ix":5},"nm":"Transform"}],"nm":"Group 11","np":3,"cix":2,"bm":0,"ix":8,"mn":"ADBE Vector Group","hd":false},{"ty":"gr","it":[{"ind":0,"ty":"sh","ix":1,"ks":{"a":1,"k":[{"i":{"x":0.167,"y":1},"o":{"x":0.333,"y":0},"t":0,"s":[{"i":[[0,0],[0,0],[0,0],[0,0],[0,0],[21.973,0]],"o":[[0,0],[0,0],[0,0],[0,0],[0,0],[-21.973,0]],"v":[[-24.763,-28.309],[-13.952,-3.084],[0,29.436],[13.941,-3.084],[24.763,-28.309],[0.002,-29.436]],"c":true}]},{"i":{"x":0.667,"y":1},"o":{"x":0.333,"y":0},"t":30,"s":[{"i":[[0,0],[0,0],[0,0],[0,0],[0,0],[21.739,0.684]],"o":[[0,0],[0,0],[0,0],[0,0],[0,0],[-21.505,-0.677]],"v":[[-10.263,-28.809],[10.298,-5.084],[34.5,22.436],[37.191,-4.834],[39.263,-28.059],[14.502,-29.686]],"c":true}]},{"i":{"x":0.667,"y":1},"o":{"x":0.794,"y":0},"t":68,"s":[{"i":[[0,0],[0,0],[0,0],[0,0],[0,0],[21.739,0.684]],"o":[[0,0],[0,0],[0,0],[0,0],[0,0],[-21.505,-0.677]],"v":[[-10.263,-28.809],[10.298,-5.084],[34.5,22.436],[37.191,-4.834],[39.263,-28.059],[14.502,-29.686]],"c":true}]},{"i":{"x":0.667,"y":1},"o":{"x":0.333,"y":0},"t":100,"s":[{"i":[[0,0],[0,0],[0,0],[0,0],[0,0],[19.739,-0.066]],"o":[[0,0],[0,0],[0,0],[0,0],[0,0],[-19.519,0.065]],"v":[[-27.263,-27.809],[-16.702,-1.584],[-5.25,29.686],[9.941,-1.584],[22.013,-27.809],[-2.748,-29.186]],"c":true}]},{"t":120,"s":[{"i":[[0,0],[0,0],[0,0],[0,0],[0,0],[21.973,0]],"o":[[0,0],[0,0],[0,0],[0,0],[0,0],[-21.973,0]],"v":[[-24.763,-28.309],[-13.952,-3.084],[0,29.436],[13.941,-3.084],[24.763,-28.309],[0.002,-29.436]],"c":true}]}],"ix":2},"nm":"Path 1","mn":"ADBE Vector Shape - Group","hd":false},{"ty":"fl","c":{"a":0,"k":[0.922,0.902,0.937,1],"ix":4,"x":"var $bm_rt;\n$bm_rt = comp('wired-lineal-653-marriage').layer('control').effect('tertiary')('Color');"},"o":{"a":0,"k":100,"ix":5},"r":1,"bm":0,"nm":".tertiary","mn":"ADBE Vector Graphic - Fill","hd":false,"cl":"tertiary"},{"ty":"tr","p":{"a":0,"k":[154.509,174.252],"ix":2},"a":{"a":0,"k":[0,0],"ix":1},"s":{"a":0,"k":[100,100],"ix":3},"r":{"a":0,"k":0,"ix":6},"o":{"a":0,"k":100,"ix":7},"sk":{"a":0,"k":0,"ix":4},"sa":{"a":0,"k":0,"ix":5},"nm":"Transform"}],"nm":"Group 9","np":2,"cix":2,"bm":0,"ix":9,"mn":"ADBE Vector Group","hd":false},{"ty":"gr","it":[{"ind":0,"ty":"sh","ix":1,"ks":{"a":1,"k":[{"i":{"x":0.167,"y":1},"o":{"x":0.333,"y":0},"t":0,"s":[{"i":[[0,0],[0,0],[0,0],[0,0],[0,0]],"o":[[0,0],[0,0],[0,0],[0,0],[0,0]],"v":[[36.097,-79.417],[-39.597,-79.417],[-36.388,79.417],[36.372,79.417],[39.597,-79.417]],"c":true}]},{"i":{"x":0.667,"y":1},"o":{"x":0.333,"y":0},"t":30,"s":[{"i":[[0,0],[0,0],[0,0],[0,0],[0,0]],"o":[[0,0],[0,0],[0,0],[0,0],[0,0]],"v":[[49.347,-79.334],[-26.347,-80.334],[-36.388,79.417],[36.372,79.417],[52.847,-79.334]],"c":true}]},{"i":{"x":0.667,"y":1},"o":{"x":0.787,"y":0},"t":68,"s":[{"i":[[0,0],[0,0],[0,0],[0,0],[0,0]],"o":[[0,0],[0,0],[0,0],[0,0],[0,0]],"v":[[49.347,-79.334],[-26.347,-80.334],[-36.388,79.417],[36.372,79.417],[52.847,-79.334]],"c":true}]},{"i":{"x":0.667,"y":1},"o":{"x":0.333,"y":0},"t":100,"s":[{"i":[[0,0],[0,0],[0,0],[0,0],[0,0]],"o":[[0,0],[0,0],[0,0],[0,0],[0,0]],"v":[[33.847,-79.334],[-41.847,-79.334],[-36.388,79.417],[36.372,79.417],[37.347,-79.334]],"c":true}]},{"t":120,"s":[{"i":[[0,0],[0,0],[0,0],[0,0],[0,0]],"o":[[0,0],[0,0],[0,0],[0,0],[0,0]],"v":[[36.097,-79.417],[-39.597,-79.417],[-36.388,79.417],[36.372,79.417],[39.597,-79.417]],"c":true}]}],"ix":2},"nm":"Path 1","mn":"ADBE Vector Shape - Group","hd":false},{"ty":"fl","c":{"a":0,"k":[0.227,0.2,0.278,1],"ix":4,"x":"var $bm_rt;\n$bm_rt = comp('wired-lineal-653-marriage').layer('control').effect('secondary')('Color');"},"o":{"a":0,"k":100,"ix":5},"r":1,"bm":0,"nm":".secondary","mn":"ADBE Vector Graphic - Fill","hd":false,"cl":"secondary"},{"ty":"tr","p":{"a":0,"k":[154.551,330.644],"ix":2},"a":{"a":0,"k":[0,0],"ix":1},"s":{"a":0,"k":[100,100],"ix":3},"r":{"a":0,"k":0,"ix":6},"o":{"a":0,"k":100,"ix":7},"sk":{"a":0,"k":0,"ix":4},"sa":{"a":0,"k":0,"ix":5},"nm":"Transform"}],"nm":"Group 10","np":2,"cix":2,"bm":0,"ix":10,"mn":"ADBE Vector Group","hd":false}],"ip":0,"op":844,"st":0,"ct":1,"bm":0},{"ddd":0,"ind":3,"ty":4,"nm":"Female 3","sr":1,"ks":{"o":{"a":0,"k":100,"ix":11},"r":{"a":0,"k":0,"ix":10},"p":{"a":0,"k":[302.423,401.806,0],"ix":2,"l":2},"a":{"a":0,"k":[337.423,436.806,0],"ix":1,"l":2},"s":{"a":0,"k":[100,100,100],"ix":6,"l":2}},"ao":0,"shapes":[{"ty":"gr","it":[{"ind":0,"ty":"sh","ix":1,"ks":{"a":1,"k":[{"i":{"x":0.163,"y":1},"o":{"x":0.333,"y":0},"t":0,"s":[{"i":[[0,0],[13.853,-28.703],[0,0]],"o":[[0,0],[-15.137,-29.285],[0,0]],"v":[[35.261,-0.035],[0.041,7.685],[-35.261,-0.035]],"c":false}]},{"i":{"x":0.667,"y":1},"o":{"x":0.333,"y":0},"t":27,"s":[{"i":[[0,0],[5.529,-26.87],[0,0]],"o":[[0,0],[-15.471,-22.37],[0,0]],"v":[[18.261,-0.099],[-29.459,7.742],[-52.261,-0.099]],"c":false}]},{"i":{"x":0.463,"y":1},"o":{"x":0.545,"y":0},"t":68,"s":[{"i":[[0,0],[5.529,-26.87],[0,0]],"o":[[0,0],[-15.471,-22.37],[0,0]],"v":[[18.261,-0.099],[-29.459,7.742],[-52.261,-0.099]],"c":false}]},{"i":{"x":0.667,"y":1},"o":{"x":0.333,"y":0},"t":94,"s":[{"i":[[0,0],[13.853,-28.703],[0,0]],"o":[[0,0],[-15.137,-29.285],[0,0]],"v":[[37.261,0.191],[2.041,7.911],[-33.261,0.191]],"c":false}]},{"t":115,"s":[{"i":[[0,0],[13.853,-28.703],[0,0]],"o":[[0,0],[-15.137,-29.285],[0,0]],"v":[[35.261,-0.035],[0.041,7.685],[-35.261,-0.035]],"c":false}]}],"ix":2},"nm":"Path 1","mn":"ADBE Vector Shape - Group","hd":false},{"ty":"st","c":{"a":0,"k":[0.071,0.075,0.192,1],"ix":3,"x":"var $bm_rt;\n$bm_rt = comp('wired-lineal-653-marriage').layer('control').effect('primary')('Color');"},"o":{"a":0,"k":100,"ix":4},"w":{"a":0,"k":3.5,"ix":5,"x":"var $bm_rt;\n$bm_rt = $bm_mul($bm_div(value, 1), comp('wired-lineal-653-marriage').layer('control').effect('stroke')('Menu'));"},"lc":2,"lj":2,"bm":0,"nm":".primary","mn":"ADBE Vector Graphic - Stroke","hd":false,"cl":"primary"},{"ty":"tr","p":{"a":0,"k":[337.43,189.127],"ix":2},"a":{"a":0,"k":[0,0],"ix":1},"s":{"a":0,"k":[100,100],"ix":3},"r":{"a":0,"k":0,"ix":6},"o":{"a":0,"k":100,"ix":7},"sk":{"a":0,"k":0,"ix":4},"sa":{"a":0,"k":0,"ix":5},"nm":"Transform"}],"nm":"Group 1","np":2,"cix":2,"bm":0,"ix":1,"mn":"ADBE Vector Group","hd":false},{"ty":"gr","it":[{"ind":0,"ty":"sh","ix":1,"ks":{"a":1,"k":[{"i":{"x":0.163,"y":1},"o":{"x":0.333,"y":0},"t":0,"s":[{"i":[[0,0],[0,0],[0,0],[0,0],[0,0],[-45.406,30.348]],"o":[[45.406,30.348],[0,0],[0,0],[0,0],[0,0],[0,0]],"v":[[30.604,-106.079],[73.903,106.079],[0.034,106.079],[-0.034,106.079],[-73.903,106.079],[-30.604,-106.079]],"c":false}]},{"i":{"x":0.667,"y":1},"o":{"x":0.333,"y":0},"t":27,"s":[{"i":[[0,0],[0,0],[0,0],[0,0],[0,0],[-45.406,30.348]],"o":[[45.406,30.348],[0,0],[0,0],[0,0],[0,0],[0,0]],"v":[[13.604,-106.143],[73.903,106.079],[0.034,106.079],[-0.034,106.079],[-73.903,106.079],[-47.604,-106.143]],"c":false}]},{"i":{"x":0.463,"y":1},"o":{"x":0.545,"y":0},"t":68,"s":[{"i":[[0,0],[0,0],[0,0],[0,0],[0,0],[-45.406,30.348]],"o":[[45.406,30.348],[0,0],[0,0],[0,0],[0,0],[0,0]],"v":[[13.604,-106.143],[73.903,106.079],[0.034,106.079],[-0.034,106.079],[-73.903,106.079],[-47.604,-106.143]],"c":false}]},{"i":{"x":0.667,"y":1},"o":{"x":0.333,"y":0},"t":94,"s":[{"i":[[0,0],[0,0],[0,0],[0,0],[0,0],[-45.406,30.348]],"o":[[45.406,30.348],[0,0],[0,0],[0,0],[0,0],[0,0]],"v":[[32.604,-105.853],[73.903,106.079],[0.034,106.079],[-0.034,106.079],[-73.903,106.079],[-28.604,-105.853]],"c":false}]},{"t":115,"s":[{"i":[[0,0],[0,0],[0,0],[0,0],[0,0],[-45.406,30.348]],"o":[[45.406,30.348],[0,0],[0,0],[0,0],[0,0],[0,0]],"v":[[30.604,-106.079],[73.903,106.079],[0.034,106.079],[-0.034,106.079],[-73.903,106.079],[-30.604,-106.079]],"c":false}]}],"ix":2},"nm":"Path 1","mn":"ADBE Vector Shape - Group","hd":false},{"ty":"st","c":{"a":0,"k":[0.071,0.075,0.192,1],"ix":3,"x":"var $bm_rt;\n$bm_rt = comp('wired-lineal-653-marriage').layer('control').effect('primary')('Color');"},"o":{"a":0,"k":100,"ix":4},"w":{"a":0,"k":3.5,"ix":5,"x":"var $bm_rt;\n$bm_rt = $bm_mul($bm_div(value, 1), comp('wired-lineal-653-marriage').layer('control').effect('stroke')('Menu'));"},"lc":2,"lj":2,"bm":0,"nm":".primary","mn":"ADBE Vector Graphic - Stroke","hd":false,"cl":"primary"},{"ty":"tr","p":{"a":0,"k":[337.423,330.727],"ix":2},"a":{"a":0,"k":[0,0],"ix":1},"s":{"a":0,"k":[100,100],"ix":3},"r":{"a":0,"k":0,"ix":6},"o":{"a":0,"k":100,"ix":7},"sk":{"a":0,"k":0,"ix":4},"sa":{"a":0,"k":0,"ix":5},"nm":"Transform"}],"nm":"Group 2","np":3,"cix":2,"bm":0,"ix":2,"mn":"ADBE Vector Group","hd":false},{"ty":"gr","it":[{"ind":0,"ty":"sh","ix":1,"ks":{"a":1,"k":[{"i":{"x":0.163,"y":1},"o":{"x":0.333,"y":0},"t":0,"s":[{"i":[[0,0],[0,0]],"o":[[0,0],[0,0]],"v":[[2.342,-17.769],[-2.342,17.769]],"c":false}]},{"i":{"x":0.667,"y":1},"o":{"x":0.333,"y":0},"t":27,"s":[{"i":[[0,0],[0,0]],"o":[[0,0],[0,0]],"v":[[-14.658,-17.833],[-19.342,17.706]],"c":false}]},{"i":{"x":0.463,"y":1},"o":{"x":0.545,"y":0},"t":68,"s":[{"i":[[0,0],[0,0]],"o":[[0,0],[0,0]],"v":[[-14.658,-17.833],[-19.342,17.706]],"c":false}]},{"i":{"x":0.667,"y":1},"o":{"x":0.333,"y":0},"t":94,"s":[{"i":[[0,0],[0,0]],"o":[[0,0],[0,0]],"v":[[4.342,-17.543],[-0.342,17.996]],"c":false}]},{"t":115,"s":[{"i":[[0,0],[0,0]],"o":[[0,0],[0,0]],"v":[[2.342,-17.769],[-2.342,17.769]],"c":false}]}],"ix":2},"nm":"Path 1","mn":"ADBE Vector Shape - Group","hd":false},{"ty":"st","c":{"a":0,"k":[0.071,0.075,0.192,1],"ix":3,"x":"var $bm_rt;\n$bm_rt = comp('wired-lineal-653-marriage').layer('control').effect('primary')('Color');"},"o":{"a":0,"k":100,"ix":4},"w":{"a":0,"k":3.5,"ix":5,"x":"var $bm_rt;\n$bm_rt = $bm_mul($bm_div(value, 1), comp('wired-lineal-653-marriage').layer('control').effect('stroke')('Menu'));"},"lc":2,"lj":2,"bm":0,"nm":".primary","mn":"ADBE Vector Graphic - Stroke","hd":false,"cl":"primary"},{"ty":"tr","p":{"a":0,"k":[370.333,206.862],"ix":2},"a":{"a":0,"k":[0,0],"ix":1},"s":{"a":0,"k":[100,100],"ix":3},"r":{"a":0,"k":0,"ix":6},"o":{"a":0,"k":100,"ix":7},"sk":{"a":0,"k":0,"ix":4},"sa":{"a":0,"k":0,"ix":5},"nm":"Transform"}],"nm":"Group 3","np":2,"cix":2,"bm":0,"ix":3,"mn":"ADBE Vector Group","hd":false},{"ty":"gr","it":[{"ind":0,"ty":"sh","ix":1,"ks":{"a":1,"k":[{"i":{"x":0.163,"y":1},"o":{"x":0.333,"y":0},"t":0,"s":[{"i":[[0,0],[0,0]],"o":[[0,0],[0,0]],"v":[[-2.342,-17.769],[2.342,17.769]],"c":false}]},{"i":{"x":0.667,"y":1},"o":{"x":0.333,"y":0},"t":27,"s":[{"i":[[0,0],[0,0]],"o":[[0,0],[0,0]],"v":[[-19.342,-17.833],[-14.658,17.706]],"c":false}]},{"i":{"x":0.463,"y":1},"o":{"x":0.545,"y":0},"t":68,"s":[{"i":[[0,0],[0,0]],"o":[[0,0],[0,0]],"v":[[-19.342,-17.833],[-14.658,17.706]],"c":false}]},{"i":{"x":0.667,"y":1},"o":{"x":0.333,"y":0},"t":94,"s":[{"i":[[0,0],[0,0]],"o":[[0,0],[0,0]],"v":[[-0.342,-17.543],[4.342,17.996]],"c":false}]},{"t":115,"s":[{"i":[[0,0],[0,0]],"o":[[0,0],[0,0]],"v":[[-2.342,-17.769],[2.342,17.769]],"c":false}]}],"ix":2},"nm":"Path 1","mn":"ADBE Vector Shape - Group","hd":false},{"ty":"st","c":{"a":0,"k":[0.071,0.075,0.192,1],"ix":3,"x":"var $bm_rt;\n$bm_rt = comp('wired-lineal-653-marriage').layer('control').effect('primary')('Color');"},"o":{"a":0,"k":100,"ix":4},"w":{"a":0,"k":3.5,"ix":5,"x":"var $bm_rt;\n$bm_rt = $bm_mul($bm_div(value, 1), comp('wired-lineal-653-marriage').layer('control').effect('stroke')('Menu'));"},"lc":2,"lj":2,"bm":0,"nm":".primary","mn":"ADBE Vector Graphic - Stroke","hd":false,"cl":"primary"},{"ty":"tr","p":{"a":0,"k":[304.511,206.862],"ix":2},"a":{"a":0,"k":[0,0],"ix":1},"s":{"a":0,"k":[100,100],"ix":3},"r":{"a":0,"k":0,"ix":6},"o":{"a":0,"k":100,"ix":7},"sk":{"a":0,"k":0,"ix":4},"sa":{"a":0,"k":0,"ix":5},"nm":"Transform"}],"nm":"Group 5","np":2,"cix":2,"bm":0,"ix":4,"mn":"ADBE Vector Group","hd":false},{"ty":"gr","it":[{"ind":0,"ty":"sh","ix":1,"ks":{"a":1,"k":[{"i":{"x":0.169,"y":1},"o":{"x":0.333,"y":0},"t":0,"s":[{"i":[[0,0],[-5.3,-12.79],[-0.17,-0.45],[0,0],[0,0],[0,0],[0,0],[-24.45,60.8],[0,0],[-7.95,5.31],[0,0],[-15.136,-29.267],[-0.002,0.005],[0,0]],"o":[[7.94,5.31],[0,0],[24.44,60.81],[0,0],[0,0],[0,0],[0,0],[0,0],[5.31,-12.79],[0,0],[0,0],[0.003,0.005],[13.853,-28.685],[0,0]],"v":[[30.605,-84.478],[50.335,-56.438],[50.875,-55.098],[73.905,127.682],[0.035,127.682],[-0.035,127.682],[-73.905,127.682],[-50.875,-55.118],[-50.345,-56.428],[-30.605,-84.478],[-35.256,-120.032],[0.04,-112.324],[0.052,-112.324],[35.265,-120.032]],"c":true}]},{"i":{"x":0.667,"y":1},"o":{"x":0.333,"y":0},"t":27,"s":[{"i":[[0,0],[-5.3,-12.79],[-0.17,-0.45],[0,0],[0,0],[0,0],[0,0],[-20.761,59.9],[0,0],[-7.95,5.31],[0,0],[-16.108,-22.463],[-0.001,0.005],[0,0]],"o":[[7.94,5.31],[0,0],[26.989,61.13],[0,0],[0,0],[0,0],[0,0],[0,0],[5.31,-12.79],[0,0],[0,0],[0.003,0.005],[5.937,-27.298],[0,0]],"v":[[13.605,-84.478],[36.835,-51.688],[37.375,-50.348],[73.905,127.682],[0.035,127.682],[-0.035,127.682],[-73.905,127.682],[-65.75,-56.993],[-65.22,-58.303],[-47.605,-84.478],[-52.256,-120.032],[-29.529,-112.13],[-29.448,-111.921],[18.391,-119.856]],"c":true}]},{"i":{"x":0.466,"y":1},"o":{"x":0.544,"y":0},"t":68,"s":[{"i":[[0,0],[-5.3,-12.79],[-0.17,-0.45],[0,0],[0,0],[0,0],[0,0],[-20.761,59.9],[0,0],[-7.95,5.31],[0,0],[-16.108,-22.463],[-0.001,0.005],[0,0]],"o":[[7.94,5.31],[0,0],[26.989,61.13],[0,0],[0,0],[0,0],[0,0],[0,0],[5.31,-12.79],[0,0],[0,0],[0.003,0.005],[5.937,-27.298],[0,0]],"v":[[13.605,-84.478],[36.835,-51.688],[37.375,-50.348],[73.905,127.682],[0.035,127.682],[-0.035,127.682],[-73.905,127.682],[-65.75,-56.993],[-65.22,-58.303],[-47.605,-84.478],[-52.256,-120.032],[-29.529,-112.13],[-29.448,-111.921],[18.391,-119.856]],"c":true}]},{"i":{"x":0.667,"y":1},"o":{"x":0.333,"y":0},"t":94,"s":[{"i":[[0,0],[-5.3,-12.79],[-0.17,-0.45],[0,0],[0,0],[0,0],[0,0],[-24.45,60.8],[0,0],[-7.95,5.31],[0,0],[-15.136,-29.267],[-0.002,0.005],[0,0]],"o":[[7.94,5.31],[0,0],[24.44,60.81],[0,0],[0,0],[0,0],[0,0],[0,0],[5.31,-12.79],[0,0],[0,0],[0.003,0.005],[13.854,-28.685],[0,0]],"v":[[32.605,-84.552],[52.335,-56.512],[52.875,-55.172],[73.905,127.858],[2.035,127.608],[1.965,127.608],[-75.155,127.858],[-48.875,-55.192],[-48.345,-56.502],[-28.605,-84.552],[-33.256,-120.106],[2.04,-112.398],[2.052,-112.398],[37.266,-120.106]],"c":true}]},{"t":115,"s":[{"i":[[0,0],[-5.3,-12.79],[-0.17,-0.45],[0,0],[0,0],[0,0],[0,0],[-24.45,60.8],[0,0],[-7.95,5.31],[0,0],[-15.136,-29.267],[-0.002,0.005],[0,0]],"o":[[7.94,5.31],[0,0],[24.44,60.81],[0,0],[0,0],[0,0],[0,0],[0,0],[5.31,-12.79],[0,0],[0,0],[0.003,0.005],[13.853,-28.685],[0,0]],"v":[[30.605,-84.478],[50.335,-56.438],[50.875,-55.098],[73.905,127.682],[0.035,127.682],[-0.035,127.682],[-73.905,127.682],[-50.875,-55.118],[-50.345,-56.428],[-30.605,-84.478],[-35.256,-120.032],[0.04,-112.324],[0.052,-112.324],[35.266,-120.032]],"c":true}]}],"ix":2},"nm":"Path 1","mn":"ADBE Vector Shape - Group","hd":false},{"ty":"fl","c":{"a":0,"k":[0.922,0.902,0.937,1],"ix":4,"x":"var $bm_rt;\n$bm_rt = comp('wired-lineal-653-marriage').layer('control').effect('tertiary')('Color');"},"o":{"a":0,"k":100,"ix":5},"r":1,"bm":0,"nm":".tertiary","mn":"ADBE Vector Graphic - Fill","hd":false,"cl":"tertiary"},{"ty":"tr","p":{"a":0,"k":[337.386,308.968],"ix":2},"a":{"a":0,"k":[0,0],"ix":1},"s":{"a":0,"k":[100,100],"ix":3},"r":{"a":0,"k":0,"ix":6},"o":{"a":0,"k":100,"ix":7},"sk":{"a":0,"k":0,"ix":4},"sa":{"a":0,"k":0,"ix":5},"nm":"Transform"}],"nm":"Group 6","np":2,"cix":2,"bm":0,"ix":5,"mn":"ADBE Vector Group","hd":false}],"ip":0,"op":844,"st":0,"ct":1,"bm":0},{"ddd":0,"ind":4,"ty":4,"nm":"Female 2","sr":1,"ks":{"o":{"a":0,"k":100,"ix":11},"r":{"a":0,"k":0,"ix":10},"p":{"a":0,"k":[302.423,401.806,0],"ix":2,"l":2},"a":{"a":0,"k":[337.423,436.806,0],"ix":1,"l":2},"s":{"a":0,"k":[100,100,100],"ix":6,"l":2}},"ao":0,"shapes":[{"ty":"gr","it":[{"ind":0,"ty":"sh","ix":1,"ks":{"a":1,"k":[{"i":{"x":0.163,"y":1},"o":{"x":0.333,"y":0},"t":0,"s":[{"i":[[0,0],[-8.348,-0.955],[0,-18.662],[0,0],[0,0],[0,12.271],[0,0]],"o":[[8.363,-0.004],[18.541,2.122],[0,0],[0,0],[-12.271,0],[0,0],[0,0]],"v":[[-28.76,-66.918],[-3.687,-65.491],[28.76,-28.831],[19.45,66.918],[28.76,66.918],[-2.769,44.699],[2.041,11.942]],"c":false}]},{"i":{"x":0.667,"y":1},"o":{"x":0.333,"y":0},"t":27,"s":[{"i":[[0,0],[-8.348,-0.955],[0,-18.662],[0,0],[0,0],[0,12.271],[0,0]],"o":[[8.363,-0.004],[18.541,2.122],[0,0],[0,0],[-12.271,0],[0,0],[0,0]],"v":[[-45.76,-66.982],[-20.687,-65.555],[11.76,-28.894],[2.45,66.854],[1.01,66.958],[-19.769,44.635],[-15.209,10.628]],"c":false}]},{"i":{"x":0.463,"y":1},"o":{"x":0.545,"y":0},"t":68,"s":[{"i":[[0,0],[-8.348,-0.955],[0,-18.662],[0,0],[0,0],[0,12.271],[0,0]],"o":[[8.363,-0.004],[18.541,2.122],[0,0],[0,0],[-12.271,0],[0,0],[0,0]],"v":[[-45.76,-66.982],[-20.687,-65.555],[11.76,-28.894],[2.45,66.854],[11.76,66.854],[-19.769,44.635],[-15.209,11.628]],"c":false}]},{"i":{"x":0.833,"y":1},"o":{"x":0.333,"y":0},"t":94,"s":[{"i":[[0,0],[-8.348,-0.955],[0,-18.662],[0,0],[0,0],[0,12.271],[0,0]],"o":[[8.363,-0.004],[18.541,2.122],[0,0],[0,0],[-12.271,0],[0,0],[0,0]],"v":[[-26.76,-66.691],[-1.687,-65.264],[30.76,-28.604],[21.45,67.144],[30.76,67.144],[-0.769,44.925],[3.791,11.168]],"c":false}]},{"t":115,"s":[{"i":[[0,0],[-8.348,-0.955],[0,-18.662],[0,0],[0,0],[0,12.271],[0,0]],"o":[[8.363,-0.004],[18.541,2.122],[0,0],[0,0],[-12.271,0],[0,0],[0,0]],"v":[[-28.76,-66.918],[-3.687,-65.491],[28.76,-28.831],[19.45,66.918],[28.76,66.918],[-2.769,44.699],[2.041,11.942]],"c":false}]}],"ix":2},"nm":"Path 1","mn":"ADBE Vector Shape - Group","hd":false},{"ty":"st","c":{"a":0,"k":[0.071,0.075,0.192,1],"ix":3,"x":"var $bm_rt;\n$bm_rt = comp('wired-lineal-653-marriage').layer('control').effect('primary')('Color');"},"o":{"a":0,"k":100,"ix":4},"w":{"a":0,"k":3.5,"ix":5,"x":"var $bm_rt;\n$bm_rt = $bm_mul($bm_div(value, 1), comp('wired-lineal-653-marriage').layer('control').effect('stroke')('Menu'));"},"lc":2,"lj":2,"bm":0,"nm":".primary","mn":"ADBE Vector Graphic - Stroke","hd":false,"cl":"primary"},{"ty":"fl","c":{"a":0,"k":[0.698,0.408,0.212,1],"ix":4,"x":"var $bm_rt;\n$bm_rt = comp('wired-lineal-653-marriage').layer('control').effect('quaternary')('Color');"},"o":{"a":0,"k":100,"ix":5},"r":1,"bm":0,"nm":".quaternary","mn":"ADBE Vector Graphic - Fill","hd":false,"cl":"quaternary"},{"ty":"tr","p":{"a":0,"k":[366.149,214.9],"ix":2},"a":{"a":0,"k":[0,0],"ix":1},"s":{"a":0,"k":[100,100],"ix":3},"r":{"a":0,"k":0,"ix":6},"o":{"a":0,"k":100,"ix":7},"sk":{"a":0,"k":0,"ix":4},"sa":{"a":0,"k":0,"ix":5},"nm":"Transform"}],"nm":"Group 6","np":3,"cix":2,"bm":0,"ix":1,"mn":"ADBE Vector Group","hd":false},{"ty":"gr","it":[{"ind":0,"ty":"sh","ix":1,"ks":{"a":1,"k":[{"i":{"x":0.163,"y":1},"o":{"x":0.333,"y":0},"t":0,"s":[{"i":[[0,0],[8.348,-0.955],[0,-18.663],[0,0],[0,0],[0,12.271],[0,0],[0,0]],"o":[[-8.363,-0.004],[-18.541,2.122],[0,0],[0,0],[12.271,0],[0,0],[0,0],[0,0]],"v":[[28.76,-66.918],[3.688,-65.491],[-28.76,-28.831],[-25.521,4.483],[-19.45,66.918],[2.769,44.699],[-2.282,10.058],[-2.041,9.942]],"c":false}]},{"i":{"x":0.667,"y":1},"o":{"x":0.333,"y":0},"t":27,"s":[{"i":[[0,0],[8.348,-0.955],[6.55,-20.006],[0,0],[0,0],[-6.602,10.344],[0,0],[0,0]],"o":[[-8.363,-0.004],[-18.541,2.122],[0,0],[0,0],[10.344,6.602],[0,0],[0,0],[0,0]],"v":[[11.76,-66.981],[-13.312,-65.555],[-48.26,-29.894],[-55.662,-5.557],[-81.986,46.117],[-51.302,39.342],[-34.865,4.134],[-23.541,-25.872]],"c":false}]},{"i":{"x":0.463,"y":1},"o":{"x":0.545,"y":0},"t":68,"s":[{"i":[[0,0],[8.348,-0.955],[6.55,-20.006],[0,0],[0,0],[-6.602,10.344],[0,0],[0,0]],"o":[[-8.363,-0.004],[-18.541,2.122],[0,0],[0,0],[10.344,6.602],[0,0],[0,0],[0,0]],"v":[[11.76,-66.981],[-13.312,-65.555],[-48.26,-29.894],[-55.662,-5.557],[-81.986,46.117],[-51.302,39.342],[-34.865,4.134],[-23.541,-25.872]],"c":false}]},{"i":{"x":0.667,"y":1},"o":{"x":0.333,"y":0},"t":94,"s":[{"i":[[0,0],[8.348,-0.955],[0,-18.663],[0,0],[0,0],[0,12.271],[0,0],[0,0]],"o":[[-8.363,-0.004],[-18.541,2.122],[0,0],[0,0],[12.271,0],[0,0],[0,0],[0,0]],"v":[[30.76,-66.691],[5.688,-65.265],[-26.76,-28.604],[-23.521,4.71],[-17.45,67.144],[4.769,44.925],[-0.032,10.785],[-0.041,10.668]],"c":false}]},{"t":115,"s":[{"i":[[0,0],[8.348,-0.955],[0,-18.663],[0,0],[0,0],[0,12.271],[0,0],[0,0]],"o":[[-8.363,-0.004],[-18.541,2.122],[0,0],[0,0],[12.271,0],[0,0],[0,0],[0,0]],"v":[[28.76,-66.918],[3.688,-65.491],[-28.76,-28.831],[-25.521,4.483],[-19.45,66.918],[2.769,44.699],[-2.282,10.058],[-2.041,9.942]],"c":false}]}],"ix":2},"nm":"Path 1","mn":"ADBE Vector Shape - Group","hd":false},{"ty":"st","c":{"a":0,"k":[0.071,0.075,0.192,1],"ix":3,"x":"var $bm_rt;\n$bm_rt = comp('wired-lineal-653-marriage').layer('control').effect('primary')('Color');"},"o":{"a":0,"k":100,"ix":4},"w":{"a":0,"k":3.5,"ix":5,"x":"var $bm_rt;\n$bm_rt = $bm_mul($bm_div(value, 1), comp('wired-lineal-653-marriage').layer('control').effect('stroke')('Menu'));"},"lc":2,"lj":2,"bm":0,"nm":".primary","mn":"ADBE Vector Graphic - Stroke","hd":false,"cl":"primary"},{"ty":"fl","c":{"a":0,"k":[0.698,0.408,0.212,1],"ix":4,"x":"var $bm_rt;\n$bm_rt = comp('wired-lineal-653-marriage').layer('control').effect('quaternary')('Color');"},"o":{"a":0,"k":100,"ix":5},"r":1,"bm":0,"nm":".quaternary","mn":"ADBE Vector Graphic - Fill","hd":false,"cl":"quaternary"},{"ty":"tr","p":{"a":0,"k":[308.71,214.9],"ix":2},"a":{"a":0,"k":[0,0],"ix":1},"s":{"a":0,"k":[100,100],"ix":3},"r":{"a":0,"k":0,"ix":6},"o":{"a":0,"k":100,"ix":7},"sk":{"a":0,"k":0,"ix":4},"sa":{"a":0,"k":0,"ix":5},"nm":"Transform"}],"nm":"Group 7","np":3,"cix":2,"bm":0,"ix":2,"mn":"ADBE Vector Group","hd":false},{"ty":"gr","it":[{"ind":0,"ty":"sh","ix":1,"ks":{"a":1,"k":[{"i":{"x":0.163,"y":1},"o":{"x":0.333,"y":0},"t":0,"s":[{"i":[[0,0],[0,0],[-0.878,2.797],[-0.722,8.387],[0,0],[0.603,-20.254],[-5.704,-4.604]],"o":[[0,0],[2.917,0.297],[1.355,-4.317],[3.983,-42.693],[0,0],[-0.599,20.135],[4.11,3.318]],"v":[[-4.494,28.39],[13.832,30.936],[20.372,26.659],[23.671,6.767],[-2.752,-30.774],[-23.993,-10.045],[-12.206,24.407]],"c":true}]},{"i":{"x":0.667,"y":1},"o":{"x":0.333,"y":0},"t":27,"s":[{"i":[[0,0],[0,0],[-1.677,3.227],[0.244,14.037],[0,0],[1.096,-27.151],[-1.833,-5.871]],"o":[[0,0],[7.021,-1.694],[2.231,-4.292],[-1.381,-23.463],[0,0],[-0.441,10.916],[1.599,5.12]],"v":[[-31.119,30.826],[-12.918,28.31],[1.372,16.283],[6.546,-10.047],[-19.752,-30.837],[-41.118,-3.921],[-37.626,26.299]],"c":true}]},{"i":{"x":0.463,"y":1},"o":{"x":0.545,"y":0},"t":68,"s":[{"i":[[0,0],[0,0],[-1.677,3.227],[0.244,14.037],[0,0],[1.096,-27.151],[-1.833,-5.871]],"o":[[0,0],[7.021,-1.694],[2.231,-4.292],[-1.381,-23.463],[0,0],[-0.441,10.916],[1.599,5.12]],"v":[[-31.119,30.826],[-12.918,28.31],[1.372,16.283],[6.546,-10.047],[-19.752,-30.837],[-41.118,-3.921],[-37.626,26.299]],"c":true}]},{"i":{"x":0.667,"y":1},"o":{"x":0.333,"y":0},"t":94,"s":[{"i":[[0,0],[0,0],[-0.878,2.797],[-0.722,8.387],[0,0],[0.603,-20.254],[-5.704,-4.604]],"o":[[0,0],[2.917,0.297],[1.355,-4.317],[3.983,-42.693],[0,0],[-0.599,20.135],[4.11,3.318]],"v":[[-2.494,28.616],[15.832,31.163],[22.372,26.886],[25.671,6.994],[-0.752,-30.547],[-21.993,-9.818],[-10.206,24.633]],"c":true}]},{"t":115,"s":[{"i":[[0,0],[0,0],[-0.878,2.797],[-0.722,8.387],[0,0],[0.603,-20.254],[-5.704,-4.604]],"o":[[0,0],[2.917,0.297],[1.355,-4.317],[3.983,-42.693],[0,0],[-0.599,20.135],[4.11,3.318]],"v":[[-4.494,28.39],[13.832,30.936],[20.372,26.659],[23.671,6.767],[-2.752,-30.774],[-23.993,-10.045],[-12.206,24.407]],"c":true}]}],"ix":2},"nm":"Path 2","mn":"ADBE Vector Shape - Group","hd":false},{"ty":"st","c":{"a":0,"k":[0.071,0.075,0.192,1],"ix":3,"x":"var $bm_rt;\n$bm_rt = comp('wired-lineal-653-marriage').layer('control').effect('primary')('Color');"},"o":{"a":0,"k":100,"ix":4},"w":{"a":0,"k":3.5,"ix":5,"x":"var $bm_rt;\n$bm_rt = $bm_mul($bm_div(value, 1), comp('wired-lineal-653-marriage').layer('control').effect('stroke')('Menu'));"},"lc":2,"lj":2,"bm":0,"nm":".primary","mn":"ADBE Vector Graphic - Stroke","hd":false,"cl":"primary"},{"ty":"tr","p":{"a":0,"k":[337.085,96.885],"ix":2},"a":{"a":0,"k":[0,0],"ix":1},"s":{"a":0,"k":[100,100],"ix":3},"r":{"a":0,"k":0,"ix":6},"o":{"a":0,"k":100,"ix":7},"sk":{"a":0,"k":0,"ix":4},"sa":{"a":0,"k":0,"ix":5},"nm":"Transform"}],"nm":"Group 14","np":2,"cix":2,"bm":0,"ix":3,"mn":"ADBE Vector Group","hd":false},{"ty":"gr","it":[{"ind":0,"ty":"sh","ix":1,"ks":{"a":1,"k":[{"i":{"x":0.178,"y":1},"o":{"x":0.333,"y":0},"t":0,"s":[{"i":[[-0.437,-0.155],[0.09,0.64],[0.33,1.28],[0.15,0.5],[0.12,0.35],[3.25,2.32],[0,0],[0,0],[2.39,-0.51],[1.57,-12.39],[0.03,-0.93],[-0.02,-1.11],[-5.743,5.244]],"o":[[-0.06,-0.68],[-0.22,-1.46],[-0.13,-0.53],[-0.11,-0.37],[-1.91,-5.58],[0,0],[-7.55,-5.42],[0,0],[-5.66,1.23],[-0.11,0.85],[-0.04,1.18],[15.725,-1.306],[5.057,8.709]],"v":[[23.875,12.166],[23.635,10.197],[22.815,6.087],[22.385,4.547],[22.035,3.467],[13.895,-8.064],[13.895,-8.073],[-2.595,-11.983],[-6.645,-11.433],[-23.625,6.087],[-23.835,8.747],[-23.865,12.177],[7.64,-0.723]],"c":true}]},{"i":{"x":0.667,"y":1},"o":{"x":0.333,"y":0},"t":27,"s":[{"i":[[-0.437,-0.155],[0.09,0.64],[0.33,1.28],[0.15,0.5],[0.092,0.359],[4.608,3.203],[0,0],[0,0],[2.372,-0.586],[3.191,-12.573],[0.03,-0.93],[-0.02,-1.11],[-5.743,5.244]],"o":[[-0.06,-0.68],[-0.22,-1.46],[-0.13,-0.53],[-0.11,-0.37],[-1.282,-5.015],[0,0],[-6.892,-4.788],[0,0],[-5.352,1.322],[-0.211,0.83],[-0.04,1.18],[15.725,-1.306],[5.057,8.709]],"v":[[6.688,11.941],[6.698,10.159],[6.502,6.111],[6.135,4.509],[5.785,3.241],[-2.293,-8.352],[-2.48,-8.361],[-19.595,-12.147],[-23.208,-11.659],[-39.75,6.049],[-40.335,8.708],[-40.802,12.139],[-9.11,-0.761]],"c":true}]},{"i":{"x":0.465,"y":1},"o":{"x":0.547,"y":0},"t":68,"s":[{"i":[[-0.437,-0.155],[0.09,0.64],[0.33,1.28],[0.15,0.5],[0.092,0.359],[4.608,3.203],[0,0],[0,0],[2.372,-0.586],[3.191,-12.573],[0.03,-0.93],[-0.02,-1.11],[-5.743,5.244]],"o":[[-0.06,-0.68],[-0.22,-1.46],[-0.13,-0.53],[-0.11,-0.37],[-1.282,-5.015],[0,0],[-6.892,-4.788],[0,0],[-5.352,1.322],[-0.211,0.83],[-0.04,1.18],[15.725,-1.306],[5.057,8.709]],"v":[[6.688,11.941],[6.698,10.159],[6.502,6.111],[6.135,4.509],[5.785,3.241],[-2.293,-8.352],[-2.48,-8.361],[-19.595,-12.147],[-23.208,-11.659],[-39.75,6.049],[-40.335,8.708],[-40.802,12.139],[-9.11,-0.761]],"c":true}]},{"i":{"x":0.667,"y":1},"o":{"x":0.333,"y":0},"t":94,"s":[{"i":[[-0.437,-0.155],[0.09,0.64],[0.33,1.28],[0.15,0.5],[0.108,0.354],[3.821,2.691],[0,0],[0,0],[2.383,-0.542],[2.252,-12.467],[0.03,-0.93],[-0.02,-1.11],[-5.743,5.244]],"o":[[-0.06,-0.68],[-0.22,-1.46],[-0.13,-0.53],[-0.11,-0.37],[-1.646,-5.343],[0,0],[-7.273,-5.154],[0,0],[-5.53,1.269],[-0.152,0.842],[-0.04,1.18],[15.725,-1.306],[5.057,8.709]],"v":[[25.397,11.982],[25.263,10.091],[24.705,6.008],[24.302,4.441],[23.952,3.283],[15.838,-8.274],[15.759,-8.284],[-0.994,-12.141],[-4.86,-11.617],[-21.656,5.982],[-22.024,8.641],[-22.237,12.071],[9.347,-0.828]],"c":true}]},{"t":115,"s":[{"i":[[-0.437,-0.155],[0.09,0.64],[0.33,1.28],[0.15,0.5],[0.12,0.35],[3.25,2.32],[0,0],[0,0],[2.39,-0.51],[1.57,-12.39],[0.03,-0.93],[-0.02,-1.11],[-5.743,5.244]],"o":[[-0.06,-0.68],[-0.22,-1.46],[-0.13,-0.53],[-0.11,-0.37],[-1.91,-5.58],[0,0],[-7.55,-5.42],[0,0],[-5.66,1.23],[-0.11,0.85],[-0.04,1.18],[15.725,-1.306],[5.057,8.709]],"v":[[23.875,12.166],[23.635,10.197],[22.815,6.087],[22.385,4.547],[22.035,3.467],[13.895,-8.064],[13.895,-8.073],[-2.595,-11.983],[-6.645,-11.433],[-23.625,6.087],[-23.835,8.747],[-23.865,12.177],[7.64,-0.723]],"c":true}]}],"ix":2},"nm":"Path 1","mn":"ADBE Vector Shape - Group","hd":false},{"ty":"fl","c":{"a":0,"k":[0.227,0.2,0.278,1],"ix":4,"x":"var $bm_rt;\n$bm_rt = comp('wired-lineal-653-marriage').layer('control').effect('secondary')('Color');"},"o":{"a":0,"k":100,"ix":5},"r":1,"bm":0,"nm":".secondary","mn":"ADBE Vector Graphic - Fill","hd":false,"cl":"secondary"},{"ty":"tr","p":{"a":0,"k":[336.934,80.212],"ix":2},"a":{"a":0,"k":[0,0],"ix":1},"s":{"a":0,"k":[100,100],"ix":3},"r":{"a":0,"k":0,"ix":6},"o":{"a":0,"k":100,"ix":7},"sk":{"a":0,"k":0,"ix":4},"sa":{"a":0,"k":0,"ix":5},"nm":"Transform"}],"nm":"Group 1","np":2,"cix":2,"bm":0,"ix":4,"mn":"ADBE Vector Group","hd":false},{"ty":"gr","it":[{"ind":0,"ty":"sh","ix":1,"ks":{"a":1,"k":[{"i":{"x":0.163,"y":1},"o":{"x":0.333,"y":0},"t":0,"s":[{"i":[[0,0],[0,0],[-0.878,2.797],[-0.722,8.387],[0,0],[0.603,-20.254],[-5.704,-4.604]],"o":[[0,0],[2.917,0.297],[1.355,-4.317],[3.983,-42.693],[0,0],[-0.599,20.135],[4.11,3.318]],"v":[[-4.494,28.39],[13.832,30.936],[20.372,26.659],[23.671,6.767],[-2.752,-30.774],[-23.993,-10.045],[-12.206,24.407]],"c":true}]},{"i":{"x":0.667,"y":1},"o":{"x":0.333,"y":0},"t":27,"s":[{"i":[[0,0],[0,0],[-1.677,3.227],[0.244,14.037],[0,0],[1.096,-27.151],[-1.833,-5.871]],"o":[[0,0],[7.021,-1.694],[2.231,-4.292],[-1.381,-23.463],[0,0],[-0.441,10.916],[1.599,5.12]],"v":[[-31.119,30.826],[-12.918,28.31],[1.372,16.283],[6.546,-10.047],[-19.752,-30.837],[-41.118,-3.921],[-37.626,26.299]],"c":true}]},{"i":{"x":0.463,"y":1},"o":{"x":0.545,"y":0},"t":68,"s":[{"i":[[0,0],[0,0],[-1.677,3.227],[0.244,14.037],[0,0],[1.096,-27.151],[-1.833,-5.871]],"o":[[0,0],[7.021,-1.694],[2.231,-4.292],[-1.381,-23.463],[0,0],[-0.441,10.916],[1.599,5.12]],"v":[[-31.119,30.826],[-12.918,28.31],[1.372,16.283],[6.546,-10.047],[-19.752,-30.837],[-41.118,-3.921],[-37.626,26.299]],"c":true}]},{"i":{"x":0.667,"y":1},"o":{"x":0.333,"y":0},"t":94,"s":[{"i":[[0,0],[0,0],[-0.878,2.797],[-0.722,8.387],[0,0],[0.603,-20.254],[-5.704,-4.604]],"o":[[0,0],[2.917,0.297],[1.355,-4.317],[3.983,-42.693],[0,0],[-0.599,20.135],[4.11,3.318]],"v":[[-2.494,28.616],[15.832,31.163],[22.372,26.886],[25.671,6.994],[-0.752,-30.547],[-21.993,-9.818],[-10.206,24.633]],"c":true}]},{"t":115,"s":[{"i":[[0,0],[0,0],[-0.878,2.797],[-0.722,8.387],[0,0],[0.603,-20.254],[-5.704,-4.604]],"o":[[0,0],[2.917,0.297],[1.355,-4.317],[3.983,-42.693],[0,0],[-0.599,20.135],[4.11,3.318]],"v":[[-4.494,28.39],[13.832,30.936],[20.372,26.659],[23.671,6.767],[-2.752,-30.774],[-23.993,-10.045],[-12.206,24.407]],"c":true}]}],"ix":2},"nm":"Path 2","mn":"ADBE Vector Shape - Group","hd":false},{"ty":"fl","c":{"a":0,"k":[0.698,0.408,0.212,1],"ix":4,"x":"var $bm_rt;\n$bm_rt = comp('wired-lineal-653-marriage').layer('control').effect('quaternary')('Color');"},"o":{"a":0,"k":100,"ix":5},"r":1,"bm":0,"nm":".quaternary","mn":"ADBE Vector Graphic - Fill","hd":false,"cl":"quaternary"},{"ty":"tr","p":{"a":0,"k":[337.085,98.885],"ix":2},"a":{"a":0,"k":[0,0],"ix":1},"s":{"a":0,"k":[100,100],"ix":3},"r":{"a":0,"k":0,"ix":6},"o":{"a":0,"k":100,"ix":7},"sk":{"a":0,"k":0,"ix":4},"sa":{"a":0,"k":0,"ix":5},"nm":"Transform"}],"nm":"Group 12","np":2,"cix":2,"bm":0,"ix":5,"mn":"ADBE Vector Group","hd":false},{"ty":"gr","it":[{"ind":0,"ty":"sh","ix":1,"ks":{"a":1,"k":[{"i":{"x":0.169,"y":1},"o":{"x":0.333,"y":0},"t":0,"s":[{"i":[[0,0],[0,0],[0,0],[0,0]],"o":[[0,0],[0,0],[0,0],[0,0]],"v":[[333.875,148],[309.5,201.5],[363.5,201.5],[341.507,148.093]],"c":true}]},{"i":{"x":0.667,"y":1},"o":{"x":0.333,"y":0},"t":27,"s":[{"i":[[0,0],[0,0],[0,0],[0,0]],"o":[[0,0],[0,0],[0,0],[0,0]],"v":[[315.875,147.75],[285.75,187.5],[341.5,201.5],[323.507,147.843]],"c":true}]},{"i":{"x":0.667,"y":1},"o":{"x":0.333,"y":0},"t":68,"s":[{"i":[[0,0],[0,0],[0,0],[0,0]],"o":[[0,0],[0,0],[0,0],[0,0]],"v":[[315.875,147.75],[285.75,187.5],[341.5,201.5],[323.507,147.843]],"c":true}]},{"i":{"x":0.667,"y":1},"o":{"x":0.333,"y":0},"t":94,"s":[{"i":[[0,0],[0,0],[0,0],[0,0]],"o":[[0,0],[0,0],[0,0],[0,0]],"v":[[333.875,148],[309.5,201.5],[363.5,201.5],[341.507,148.093]],"c":true}]},{"t":115,"s":[{"i":[[0,0],[0,0],[0,0],[0,0]],"o":[[0,0],[0,0],[0,0],[0,0]],"v":[[333.875,148],[309.5,201.5],[363.5,201.5],[341.507,148.093]],"c":true}]}],"ix":2},"nm":"Path 1","mn":"ADBE Vector Shape - Group","hd":false},{"ty":"fl","c":{"a":0,"k":[0.698,0.408,0.212,1],"ix":4,"x":"var $bm_rt;\n$bm_rt = comp('wired-lineal-653-marriage').layer('control').effect('quaternary')('Color');"},"o":{"a":0,"k":100,"ix":5},"r":1,"bm":0,"nm":".quaternary","mn":"ADBE Vector Graphic - Fill","hd":false,"cl":"quaternary"},{"ty":"tr","p":{"a":0,"k":[0,0],"ix":2},"a":{"a":0,"k":[0,0],"ix":1},"s":{"a":0,"k":[100,100],"ix":3},"r":{"a":0,"k":0,"ix":6},"o":{"a":0,"k":100,"ix":7},"sk":{"a":0,"k":0,"ix":4},"sa":{"a":0,"k":0,"ix":5},"nm":"Transform"}],"nm":"Shape 1","np":2,"cix":2,"bm":0,"ix":6,"mn":"ADBE Vector Group","hd":false},{"ty":"gr","it":[{"ind":0,"ty":"sh","ix":1,"ks":{"a":1,"k":[{"i":{"x":0.833,"y":0.833},"o":{"x":0.333,"y":0},"t":0,"s":[{"i":[[0,0],[0,0],[-24.02,0],[0,0],[0,-24.02],[0,0]],"o":[[0,0],[0,-24.02],[0,0],[24.02,0],[0,0],[0,0]],"v":[[-50.821,-13.414],[-50.821,-68.325],[-7.148,-111.998],[7.148,-111.998],[50.821,-68.325],[50.821,-13.414]],"c":false}]},{"i":{"x":0.667,"y":1},"o":{"x":0.167,"y":0.167},"t":5,"s":[{"i":[[0,0],[0,0],[-24.02,0],[0,0],[-1.529,-24.739],[0,0]],"o":[[0,0],[0,-24.02],[0,0],[24.02,0],[0,0],[0,0]],"v":[[-52.571,-16.87],[-53.607,-68.691],[-12.697,-112.019],[1.598,-112.019],[45.963,-68.345],[47.485,-11.383]],"c":false}]},{"i":{"x":0.833,"y":0.833},"o":{"x":0.333,"y":0},"t":8,"s":[{"i":[[0,0],[0,0],[-24.02,0],[0,0],[-2.21,-25.058],[0,0]],"o":[[0,0],[0,-24.02],[0,0],[24.02,0],[0,0],[0,0]],"v":[[-53.349,-20.436],[-54.847,-68.854],[-15.169,-112.028],[-0.873,-112.028],[43.799,-68.355],[46.171,-5.202]],"c":false}]},{"i":{"x":0.667,"y":1},"o":{"x":0.167,"y":0.167},"t":15,"s":[{"i":[[0,0],[0,0],[-24.02,0],[0,0],[-1.531,-24.739],[0,0]],"o":[[0,0],[0,-24.02],[0,0],[24.02,0],[0,0],[0,0]],"v":[[-58.745,-19.984],[-59.14,-68.711],[-17.927,-112.039],[-3.631,-112.039],[39.966,-68.672],[40.63,-5.173]],"c":false}]},{"i":{"x":0.667,"y":1},"o":{"x":0.333,"y":0},"t":27,"s":[{"i":[[0,0],[0,0],[-24.02,0],[0,0],[0,-24.02],[0,0]],"o":[[0,0],[0,-24.02],[0,0],[24.02,0],[0,0],[0,0]],"v":[[-71.321,-7.978],[-68.821,-68.388],[-24.148,-112.062],[-9.852,-112.062],[31.321,-69.388],[27.321,-20.978]],"c":false}]},{"i":{"x":0.667,"y":1},"o":{"x":0.333,"y":0},"t":42.594,"s":[{"i":[[0,0],[0,0],[-24.021,0],[0,0],[0,-24.02],[0,0]],"o":[[0,0],[0,-24.02],[0,0],[24.02,0],[0,0],[0,0]],"v":[[-64.821,-16.728],[-67.821,-68.388],[-24.148,-112.062],[-9.852,-112.062],[33.821,-68.388],[37.071,-8.228]],"c":false}]},{"i":{"x":0.833,"y":0.833},"o":{"x":0.333,"y":0},"t":68,"s":[{"i":[[0,0],[0,0],[-24.021,0],[0,0],[0,-24.02],[0,0]],"o":[[0,0],[0,-24.02],[0,0],[24.02,0],[0,0],[0,0]],"v":[[-67.821,-13.478],[-67.821,-68.388],[-24.148,-112.062],[-9.852,-112.062],[33.821,-68.388],[33.821,-13.478]],"c":false}]},{"i":{"x":0.833,"y":0.833},"o":{"x":0.167,"y":0.167},"t":76,"s":[{"i":[[0,0],[0,0],[-24.021,0],[0,0],[1.644,-24.05],[0,0]],"o":[[0,0],[1.716,-23.8],[0,0],[24.02,0],[0,0],[0,0]],"v":[[-65.838,-12.12],[-62.838,-68.78],[-18.414,-111.958],[-4.119,-111.958],[36.055,-68.53],[33.305,-17.494]],"c":false}]},{"i":{"x":0.667,"y":1},"o":{"x":0.167,"y":0.167},"t":80,"s":[{"i":[[0,0],[0,0],[-24.021,0],[0,0],[2.692,-24.068],[0,0]],"o":[[0,0],[2.809,-23.659],[0,0],[24.02,0],[0,0],[0,0]],"v":[[-64.768,-8.573],[-59.663,-69.029],[-14.762,-111.891],[-0.467,-111.891],[37.477,-68.62],[33.225,-19.817]],"c":false}]},{"i":{"x":0.833,"y":0.833},"o":{"x":0.333,"y":0},"t":84,"s":[{"i":[[0,0],[0,0],[-24.021,0],[0,0],[3.289,-24.079],[0,0]],"o":[[0,0],[3.431,-23.579],[0,0],[24.02,0],[0,0],[0,0]],"v":[[-63.855,-0.886],[-57.855,-69.171],[-12.681,-111.854],[1.614,-111.854],[38.288,-68.671],[32.538,-23.761]],"c":false}]},{"i":{"x":0.833,"y":0.833},"o":{"x":0.167,"y":0.167},"t":91,"s":[{"i":[[0,0],[0,0],[-24.021,0],[0,0],[1.314,-24.564],[0,0]],"o":[[0,0],[0.279,-24.261],[0,0],[24.02,0],[0,0],[0,0]],"v":[[-55.673,1.433],[-53.722,-68.946],[-9.725,-111.822],[4.57,-111.822],[43.402,-68.446],[41.423,-23.758]],"c":false}]},{"i":{"x":0.667,"y":1},"o":{"x":0.167,"y":0.167},"t":96,"s":[{"i":[[0,0],[0,0],[-24.021,0],[0,0],[-0.753,-25.072],[0,0]],"o":[[0,0],[-3.02,-24.974],[0,0],[24.02,0],[0,0],[0,0]],"v":[[-47.701,-14.253],[-49.396,-68.711],[-6.632,-111.788],[7.664,-111.788],[48.754,-68.211],[51.654,-14.685]],"c":false}]},{"i":{"x":0.667,"y":1},"o":{"x":0.333,"y":0},"t":100.365,"s":[{"i":[[0,0],[0,0],[-24.021,0],[0,0],[-1.745,-25.316],[0,0]],"o":[[0,0],[-4.602,-25.316],[0,0],[24.02,0],[0,0],[0,0]],"v":[[-43.321,-19.188],[-47.321,-68.598],[-5.148,-111.772],[9.148,-111.772],[51.321,-68.098],[55.821,-7.188]],"c":false}]},{"t":120,"s":[{"i":[[0,0],[0,0],[-24.021,0],[0,0],[0,-24.02],[0,0]],"o":[[0,0],[0,-24.02],[0,0],[24.02,0],[0,0],[0,0]],"v":[[-50.821,-13.414],[-50.821,-68.325],[-7.148,-111.998],[7.148,-111.998],[50.821,-68.325],[50.821,-13.414]],"c":false}]}],"ix":2},"nm":"Path 1","mn":"ADBE Vector Shape - Group","hd":false},{"ty":"st","c":{"a":0,"k":[0.071,0.075,0.192,1],"ix":3,"x":"var $bm_rt;\n$bm_rt = comp('wired-lineal-653-marriage').layer('control').effect('primary')('Color');"},"o":{"a":0,"k":100,"ix":4},"w":{"a":0,"k":3.5,"ix":5,"x":"var $bm_rt;\n$bm_rt = $bm_mul($bm_div(value, 1), comp('wired-lineal-653-marriage').layer('control').effect('stroke')('Menu'));"},"lc":2,"lj":2,"bm":0,"nm":".primary","mn":"ADBE Vector Graphic - Stroke","hd":false,"cl":"primary"},{"ty":"fl","c":{"a":0,"k":[0.922,0.902,0.937,1],"ix":4,"x":"var $bm_rt;\n$bm_rt = comp('wired-lineal-653-marriage').layer('control').effect('tertiary')('Color');"},"o":{"a":0,"k":50,"ix":5},"r":1,"bm":1,"nm":".tertiary","mn":"ADBE Vector Graphic - Fill","hd":false,"cl":"tertiary"},{"ty":"fl","c":{"a":0,"k":[0.922,0.902,0.937,1],"ix":4,"x":"var $bm_rt;\n$bm_rt = comp('wired-lineal-653-marriage').layer('control').effect('tertiary')('Color');"},"o":{"a":0,"k":100,"ix":5},"r":1,"bm":0,"nm":".tertiary","mn":"ADBE Vector Graphic - Fill","hd":false,"cl":"tertiary"},{"ty":"tr","p":{"a":0,"k":[337.423,178.914],"ix":2},"a":{"a":0,"k":[0,0],"ix":1},"s":{"a":0,"k":[100,100],"ix":3},"r":{"a":0,"k":0,"ix":6},"o":{"a":0,"k":100,"ix":7},"sk":{"a":0,"k":0,"ix":4},"sa":{"a":0,"k":0,"ix":5},"nm":"Transform"}],"nm":"Group 13","np":4,"cix":2,"bm":0,"ix":7,"mn":"ADBE Vector Group","hd":false}],"ip":0,"op":844,"st":0,"ct":1,"bm":0}]}],"layers":[{"ddd":0,"ind":1,"ty":3,"nm":"control","sr":1,"ks":{"o":{"a":0,"k":0,"ix":11},"r":{"a":0,"k":0,"ix":10},"p":{"a":0,"k":[0,0],"ix":2,"l":2},"a":{"a":0,"k":[0,0,0],"ix":1,"l":2},"s":{"a":0,"k":[100,100,100],"ix":6,"l":2}},"ao":0,"ef":[{"ty":5,"nm":"stroke","np":3,"mn":"Pseudo/@@SBw0oE+/RVCeTtrlszIn/Q","ix":1,"en":1,"ef":[{"ty":7,"nm":"Menu","mn":"Pseudo/@@SBw0oE+/RVCeTtrlszIn/Q-0001","ix":1,"v":{"a":0,"k":1,"ix":1}}]},{"ty":5,"nm":"primary","np":3,"mn":"ADBE Color Control","ix":2,"en":1,"ef":[{"ty":2,"nm":"Color","mn":"ADBE Color Control-0001","ix":1,"v":{"a":0,"k":[0.071,0.075,0.192],"ix":1}}]},{"ty":5,"nm":"secondary","np":3,"mn":"ADBE Color Control","ix":3,"en":1,"ef":[{"ty":2,"nm":"Color","mn":"ADBE Color Control-0001","ix":1,"v":{"a":0,"k":[0.227,0.2,0.278],"ix":1}}]},{"ty":5,"nm":"tertiary","np":3,"mn":"ADBE Color Control","ix":4,"en":1,"ef":[{"ty":2,"nm":"Color","mn":"ADBE Color Control-0001","ix":1,"v":{"a":0,"k":[0.922,0.902,0.937],"ix":1}}]},{"ty":5,"nm":"quaternary","np":3,"mn":"ADBE Color Control","ix":5,"en":1,"ef":[{"ty":2,"nm":"Color","mn":"ADBE Color Control-0001","ix":1,"v":{"a":0,"k":[0.698,0.408,0.212],"ix":1}}]},{"ty":5,"nm":"quinary","np":3,"mn":"ADBE Color Control","ix":6,"en":1,"ef":[{"ty":2,"nm":"Color","mn":"ADBE Color Control-0001","ix":1,"v":{"a":0,"k":[0.392,0.431,0.471],"ix":1}}]},{"ty":5,"nm":"senary","np":3,"mn":"ADBE Color Control","ix":7,"en":1,"ef":[{"ty":2,"nm":"Color","mn":"ADBE Color Control-0001","ix":1,"v":{"a":0,"k":[0.835,0.624,0.502],"ix":1}}]},{"ty":5,"nm":"septenary","np":3,"mn":"ADBE Color Control","ix":8,"en":1,"ef":[{"ty":2,"nm":"Color","mn":"ADBE Color Control-0001","ix":1,"v":{"a":0,"k":[0.976,0.788,0.753],"ix":1}}]}],"ip":0,"op":121,"st":0,"bm":0},{"ddd":0,"ind":2,"ty":0,"nm":"hover-pinch","refId":"comp_0","sr":1,"ks":{"o":{"a":0,"k":100,"ix":11},"r":{"a":0,"k":0,"ix":10},"p":{"a":0,"k":[215,215,0],"ix":2,"l":2},"a":{"a":0,"k":[215,215,0],"ix":1,"l":2},"s":{"a":0,"k":[100,100,100],"ix":6,"l":2}},"ao":0,"w":430,"h":430,"ip":0,"op":130,"st":0,"bm":0}],"markers":[{"tm":0,"cm":"default:hover-pinch","dr":120}],"props":{}}